{
  "fio version" : "fio-3.26-38-g3277",
  "timestamp" : 1622527248,
  "timestamp_ms" : 1622527248640,
  "time" : "Tue Jun  1 06:00:48 2021",
  "global options" : {
    "directory" : "/test-volume",
    "bs" : "8192",
    "fallocate" : "none",
    "runtime" : "30",
    "time_based" : "1",
    "ioengine" : "libaio",
    "iodepth" : "8",
    "direct" : "0",
    "buffered" : "1",
    "invalidate" : "1",
    "ramp_time" : "0",
    "thread" : "0",
    "numjobs" : "2",
    "group_reporting" : "1",
    "filesize" : "2G",
    "size" : "2G",
    "filename_format" : "$jobnum.dat"
  },
  "jobs" : [
    {
      "jobname" : "fio-job",
      "groupid" : 0,
      "error" : 0,
      "eta" : 0,
      "elapsed" : 31,
      "job options" : {
        "rw" : "randwrite"
      },
      "read" : {
        "io_bytes" : 0,
        "io_kbytes" : 0,
        "bw_bytes" : 0,
        "bw" : 0,
        "iops" : 0.000000,
        "runtime" : 0,
        "total_ios" : 0,
        "short_ios" : 0,
        "drop_ios" : 0,
        "slat_ns" : {
          "min" : 0,
          "max" : 0,
          "mean" : 0.000000,
          "stddev" : 0.000000,
          "N" : 0
        },
        "clat_ns" : {
          "min" : 0,
          "max" : 0,
          "mean" : 0.000000,
          "stddev" : 0.000000,
          "N" : 0
        },
        "lat_ns" : {
          "min" : 0,
          "max" : 0,
          "mean" : 0.000000,
          "stddev" : 0.000000,
          "N" : 0
        },
        "bw_min" : 0,
        "bw_max" : 0,
        "bw_agg" : 0.000000,
        "bw_mean" : 0.000000,
        "bw_dev" : 0.000000,
        "bw_samples" : 0,
        "iops_min" : 0,
        "iops_max" : 0,
        "iops_mean" : 0.000000,
        "iops_stddev" : 0.000000,
        "iops_samples" : 0
      },
      "write" : {
        "io_bytes" : 78301593600,
        "io_kbytes" : 76466400,
        "bw_bytes" : 2609966121,
        "bw" : 2548795,
        "iops" : 318599.380021,
        "runtime" : 30001,
        "total_ios" : 9558300,
        "short_ios" : 0,
        "drop_ios" : 0,
        "slat_ns" : {
          "min" : 1574,
          "max" : 8031443,
          "mean" : 4729.531812,
          "stddev" : 94563.298380,
          "N" : 9558300
        },
        "clat_ns" : {
          "min" : 1212,
          "max" : 8063936,
          "mean" : 44566.277756,
          "stddev" : 289318.908956,
          "N" : 9558300,
          "percentile" : {
            "1.000000" : 20096,
            "5.000000" : 20608,
            "10.000000" : 20608,
            "20.000000" : 20864,
            "30.000000" : 21120,
            "40.000000" : 21120,
            "50.000000" : 21376,
            "60.000000" : 21632,
            "70.000000" : 21888,
            "80.000000" : 22400,
            "90.000000" : 24960,
            "95.000000" : 27008,
            "99.000000" : 37632,
            "99.500000" : 2539520,
            "99.900000" : 4046848,
            "99.950000" : 4620288,
            "99.990000" : 5341184
          },
          "bins" : {
            "1208" : 1,
            "1464" : 1,
            "4128" : 1,
            "4320" : 1,
            "7008" : 1,
            "7392" : 1,
            "9792" : 1,
            "10176" : 1,
            "12480" : 1,
            "12992" : 1,
            "15552" : 1,
            "16064" : 1,
            "18304" : 1,
            "18816" : 6,
            "19072" : 89,
            "19328" : 1114,
            "19584" : 6510,
            "19840" : 26700,
            "20096" : 99878,
            "20352" : 318092,
            "20608" : 741106,
            "20864" : 1213601,
            "21120" : 1482693,
            "21376" : 1428003,
            "21632" : 1119113,
            "21888" : 751604,
            "22144" : 441044,
            "22400" : 252203,
            "22656" : 161520,
            "22912" : 127466,
            "23168" : 111670,
            "23424" : 91069,
            "23680" : 70095,
            "23936" : 50324,
            "24192" : 36342,
            "24448" : 27518,
            "24704" : 23376,
            "24960" : 28333,
            "25216" : 47757,
            "25472" : 75627,
            "25728" : 90422,
            "25984" : 83175,
            "26240" : 63888,
            "26496" : 46759,
            "26752" : 37881,
            "27008" : 36148,
            "27264" : 37186,
            "27520" : 38807,
            "27776" : 38363,
            "28032" : 35798,
            "28288" : 32595,
            "28544" : 28657,
            "28800" : 24324,
            "29056" : 20315,
            "29312" : 16705,
            "29568" : 13275,
            "29824" : 10659,
            "30080" : 8671,
            "30336" : 7493,
            "30592" : 6507,
            "30848" : 5621,
            "31104" : 4842,
            "31360" : 4150,
            "31616" : 3623,
            "31872" : 3178,
            "32128" : 2620,
            "32384" : 2416,
            "32640" : 2293,
            "33024" : 3914,
            "33536" : 3233,
            "34048" : 2772,
            "34560" : 2578,
            "35072" : 2381,
            "35584" : 2230,
            "36096" : 2056,
            "36608" : 1831,
            "37120" : 1623,
            "37632" : 1481,
            "38144" : 1263,
            "38656" : 1024,
            "39168" : 861,
            "39680" : 769,
            "40192" : 797,
            "40704" : 746,
            "41216" : 853,
            "41728" : 1117,
            "42240" : 1258,
            "42752" : 1560,
            "43264" : 1866,
            "43776" : 1935,
            "44288" : 1861,
            "44800" : 1573,
            "45312" : 1313,
            "45824" : 932,
            "46336" : 715,
            "46848" : 544,
            "47360" : 486,
            "47872" : 426,
            "48384" : 367,
            "48896" : 386,
            "49408" : 326,
            "49920" : 309,
            "50432" : 311,
            "50944" : 271,
            "51456" : 212,
            "51968" : 187,
            "52480" : 175,
            "52992" : 181,
            "53504" : 126,
            "54016" : 128,
            "54528" : 128,
            "55040" : 133,
            "55552" : 123,
            "56064" : 136,
            "56576" : 111,
            "57088" : 75,
            "57600" : 96,
            "58112" : 82,
            "58624" : 90,
            "59136" : 87,
            "59648" : 92,
            "60160" : 76,
            "60672" : 72,
            "61184" : 83,
            "61696" : 89,
            "62208" : 66,
            "62720" : 59,
            "63232" : 74,
            "63744" : 64,
            "64256" : 59,
            "64768" : 70,
            "65280" : 75,
            "66048" : 160,
            "67072" : 280,
            "68096" : 389,
            "69120" : 397,
            "70144" : 428,
            "71168" : 397,
            "72192" : 261,
            "73216" : 240,
            "74240" : 191,
            "75264" : 170,
            "76288" : 89,
            "77312" : 116,
            "78336" : 86,
            "79360" : 71,
            "80384" : 54,
            "81408" : 33,
            "82432" : 26,
            "83456" : 17,
            "84480" : 8,
            "85504" : 20,
            "86528" : 23,
            "87552" : 15,
            "88576" : 14,
            "89600" : 11,
            "90624" : 9,
            "91648" : 11,
            "92672" : 10,
            "93696" : 4,
            "94720" : 8,
            "95744" : 3,
            "96768" : 8,
            "97792" : 3,
            "98816" : 3,
            "99840" : 1,
            "100864" : 6,
            "101888" : 4,
            "102912" : 11,
            "103936" : 13,
            "104960" : 6,
            "105984" : 2,
            "107008" : 2,
            "108032" : 11,
            "109056" : 4,
            "110080" : 3,
            "111104" : 3,
            "112128" : 7,
            "113152" : 5,
            "114176" : 2,
            "115200" : 3,
            "116224" : 4,
            "117248" : 9,
            "118272" : 2,
            "119296" : 9,
            "120320" : 18,
            "121344" : 23,
            "122368" : 7,
            "123392" : 13,
            "124416" : 26,
            "125440" : 10,
            "126464" : 1,
            "127488" : 14,
            "128512" : 8,
            "129536" : 16,
            "130560" : 11,
            "132096" : 16,
            "134144" : 15,
            "136192" : 24,
            "138240" : 7,
            "140288" : 10,
            "142336" : 11,
            "144384" : 15,
            "146432" : 16,
            "148480" : 1,
            "150528" : 4,
            "154624" : 5,
            "156672" : 5,
            "158720" : 5,
            "160768" : 1,
            "164864" : 1,
            "166912" : 3,
            "168960" : 1,
            "171008" : 8,
            "173056" : 2,
            "175104" : 3,
            "177152" : 1,
            "179200" : 2,
            "185344" : 3,
            "189440" : 1,
            "193536" : 1,
            "195584" : 2,
            "197632" : 1,
            "199680" : 1,
            "201728" : 1,
            "205824" : 1,
            "207872" : 2,
            "211968" : 2,
            "214016" : 1,
            "220160" : 1,
            "224256" : 1,
            "226304" : 1,
            "230400" : 1,
            "232448" : 1,
            "234496" : 1,
            "236544" : 1,
            "238592" : 7,
            "240640" : 2,
            "242688" : 4,
            "244736" : 3,
            "246784" : 7,
            "248832" : 1,
            "250880" : 6,
            "252928" : 3,
            "254976" : 1,
            "257024" : 7,
            "259072" : 7,
            "261120" : 3,
            "264192" : 14,
            "268288" : 2,
            "272384" : 1,
            "276480" : 14,
            "280576" : 3,
            "284672" : 7,
            "288768" : 3,
            "292864" : 1,
            "296960" : 4,
            "301056" : 6,
            "309248" : 7,
            "329728" : 6,
            "337920" : 2,
            "342016" : 6,
            "346112" : 1,
            "350208" : 8,
            "362496" : 1,
            "366592" : 1,
            "370688" : 19,
            "374784" : 1,
            "378880" : 2,
            "382976" : 7,
            "387072" : 11,
            "391168" : 27,
            "399360" : 2,
            "407552" : 1,
            "415744" : 3,
            "419840" : 6,
            "432128" : 2,
            "436224" : 1,
            "440320" : 5,
            "444416" : 5,
            "448512" : 13,
            "452608" : 4,
            "456704" : 5,
            "460800" : 12,
            "468992" : 7,
            "473088" : 9,
            "489472" : 7,
            "497664" : 1,
            "501760" : 8,
            "505856" : 22,
            "509952" : 1,
            "514048" : 7,
            "518144" : 1,
            "522240" : 8,
            "528384" : 6,
            "536576" : 1,
            "544768" : 13,
            "552960" : 15,
            "561152" : 14,
            "569344" : 9,
            "577536" : 9,
            "585728" : 4,
            "593920" : 20,
            "602112" : 13,
            "610304" : 27,
            "618496" : 24,
            "626688" : 8,
            "634880" : 8,
            "643072" : 50,
            "651264" : 20,
            "659456" : 14,
            "667648" : 33,
            "675840" : 104,
            "684032" : 100,
            "692224" : 72,
            "700416" : 62,
            "708608" : 39,
            "716800" : 26,
            "724992" : 24,
            "733184" : 33,
            "741376" : 43,
            "749568" : 32,
            "757760" : 58,
            "765952" : 61,
            "774144" : 29,
            "782336" : 36,
            "790528" : 40,
            "798720" : 19,
            "806912" : 23,
            "815104" : 18,
            "823296" : 18,
            "831488" : 36,
            "839680" : 30,
            "847872" : 47,
            "856064" : 49,
            "864256" : 33,
            "872448" : 29,
            "880640" : 18,
            "888832" : 44,
            "897024" : 32,
            "905216" : 32,
            "913408" : 32,
            "921600" : 56,
            "929792" : 23,
            "937984" : 32,
            "946176" : 45,
            "954368" : 46,
            "962560" : 56,
            "970752" : 46,
            "978944" : 101,
            "987136" : 64,
            "995328" : 104,
            "1003520" : 119,
            "1011712" : 82,
            "1019904" : 55,
            "1028096" : 42,
            "1036288" : 20,
            "1044480" : 77,
            "1056768" : 68,
            "1073152" : 112,
            "1089536" : 99,
            "1105920" : 57,
            "1122304" : 36,
            "1138688" : 94,
            "1155072" : 98,
            "1171456" : 82,
            "1187840" : 49,
            "1204224" : 95,
            "1220608" : 78,
            "1236992" : 70,
            "1253376" : 96,
            "1269760" : 107,
            "1286144" : 165,
            "1302528" : 202,
            "1318912" : 177,
            "1335296" : 73,
            "1351680" : 91,
            "1368064" : 82,
            "1384448" : 85,
            "1400832" : 64,
            "1417216" : 75,
            "1433600" : 60,
            "1449984" : 63,
            "1466368" : 83,
            "1482752" : 81,
            "1499136" : 99,
            "1515520" : 160,
            "1531904" : 75,
            "1548288" : 111,
            "1564672" : 153,
            "1581056" : 346,
            "1597440" : 263,
            "1613824" : 272,
            "1630208" : 218,
            "1646592" : 131,
            "1662976" : 169,
            "1679360" : 126,
            "1695744" : 115,
            "1712128" : 109,
            "1728512" : 131,
            "1744896" : 147,
            "1761280" : 118,
            "1777664" : 148,
            "1794048" : 135,
            "1810432" : 138,
            "1826816" : 142,
            "1843200" : 102,
            "1859584" : 102,
            "1875968" : 359,
            "1892352" : 410,
            "1908736" : 212,
            "1925120" : 285,
            "1941504" : 215,
            "1957888" : 218,
            "1974272" : 97,
            "1990656" : 114,
            "2007040" : 123,
            "2023424" : 173,
            "2039808" : 123,
            "2056192" : 102,
            "2072576" : 114,
            "2088960" : 115,
            "2113536" : 268,
            "2146304" : 277,
            "2179072" : 380,
            "2211840" : 541,
            "2244608" : 697,
            "2277376" : 267,
            "2310144" : 276,
            "2342912" : 242,
            "2375680" : 234,
            "2408448" : 267,
            "2441216" : 298,
            "2473984" : 352,
            "2506752" : 526,
            "2539520" : 669,
            "2572288" : 264,
            "2605056" : 347,
            "2637824" : 193,
            "2670592" : 206,
            "2703360" : 273,
            "2736128" : 288,
            "2768896" : 319,
            "2801664" : 445,
            "2834432" : 541,
            "2867200" : 414,
            "2899968" : 282,
            "2932736" : 290,
            "2965504" : 274,
            "2998272" : 220,
            "3031040" : 237,
            "3063808" : 296,
            "3096576" : 309,
            "3129344" : 558,
            "3162112" : 466,
            "3194880" : 281,
            "3227648" : 297,
            "3260416" : 218,
            "3293184" : 215,
            "3325952" : 251,
            "3358720" : 361,
            "3391488" : 212,
            "3424256" : 447,
            "3457024" : 538,
            "3489792" : 228,
            "3522560" : 229,
            "3555328" : 232,
            "3588096" : 155,
            "3620864" : 168,
            "3653632" : 172,
            "3686400" : 151,
            "3719168" : 165,
            "3751936" : 266,
            "3784704" : 360,
            "3817472" : 178,
            "3850240" : 186,
            "3883008" : 143,
            "3915776" : 125,
            "3948544" : 170,
            "3981312" : 109,
            "4014080" : 64,
            "4046848" : 26800,
            "4079616" : 1063,
            "4112384" : 253,
            "4145152" : 90,
            "4177920" : 163,
            "4227072" : 270,
            "4292608" : 369,
            "4358144" : 560,
            "4423680" : 270,
            "4489216" : 248,
            "4554752" : 324,
            "4620288" : 346,
            "4685824" : 542,
            "4751360" : 276,
            "4816896" : 228,
            "4882432" : 243,
            "4947968" : 430,
            "5013504" : 368,
            "5079040" : 267,
            "5144576" : 216,
            "5210112" : 305,
            "5275648" : 528,
            "5341184" : 242,
            "5406720" : 206,
            "5472256" : 131,
            "5537792" : 142,
            "5603328" : 214,
            "5668864" : 56,
            "5734400" : 28,
            "5799936" : 19,
            "5865472" : 31,
            "5931008" : 7,
            "8028160" : 58,
            "8093696" : 6
          }
        },
        "lat_ns" : {
          "min" : 3456,
          "max" : 8068696,
          "mean" : 49451.660669,
          "stddev" : 304772.788282,
          "N" : 9558300
        },
        "bw_min" : 2059440,
        "bw_max" : 2666560,
        "bw_agg" : 100.000000,
        "bw_mean" : 2549211.389831,
        "bw_dev" : 67524.797402,
        "bw_samples" : 118,
        "iops_min" : 257430,
        "iops_max" : 333320,
        "iops_mean" : 318651.423729,
        "iops_stddev" : 8440.599675,
        "iops_samples" : 118
      },
      "trim" : {
        "io_bytes" : 0,
        "io_kbytes" : 0,
        "bw_bytes" : 0,
        "bw" : 0,
        "iops" : 0.000000,
        "runtime" : 0,
        "total_ios" : 0,
        "short_ios" : 0,
        "drop_ios" : 0,
        "slat_ns" : {
          "min" : 0,
          "max" : 0,
          "mean" : 0.000000,
          "stddev" : 0.000000,
          "N" : 0
        },
        "clat_ns" : {
          "min" : 0,
          "max" : 0,
          "mean" : 0.000000,
          "stddev" : 0.000000,
          "N" : 0
        },
        "lat_ns" : {
          "min" : 0,
          "max" : 0,
          "mean" : 0.000000,
          "stddev" : 0.000000,
          "N" : 0
        },
        "bw_min" : 0,
        "bw_max" : 0,
        "bw_agg" : 0.000000,
        "bw_mean" : 0.000000,
        "bw_dev" : 0.000000,
        "bw_samples" : 0,
        "iops_min" : 0,
        "iops_max" : 0,
        "iops_mean" : 0.000000,
        "iops_stddev" : 0.000000,
        "iops_samples" : 0
      },
      "sync" : {
        "total_ios" : 0,
        "lat_ns" : {
          "min" : 0,
          "max" : 0,
          "mean" : 0.000000,
          "stddev" : 0.000000,
          "N" : 0
        }
      },
      "job_runtime" : 60000,
      "usr_cpu" : 12.516667,
      "sys_cpu" : 37.091667,
      "ctx" : 14038,
      "majf" : 0,
      "minf" : 22,
      "iodepth_level" : {
        "1" : 0.100000,
        "2" : 0.100000,
        "4" : 0.100000,
        "8" : 99.999854,
        "16" : 0.000000,
        "32" : 0.000000,
        ">=64" : 0.000000
      },
      "iodepth_submit" : {
        "0" : 0.000000,
        "4" : 100.000000,
        "8" : 0.000000,
        "16" : 0.000000,
        "32" : 0.000000,
        "64" : 0.000000,
        ">=64" : 0.000000
      },
      "iodepth_complete" : {
        "0" : 0.000000,
        "4" : 99.999979,
        "8" : 0.100000,
        "16" : 0.000000,
        "32" : 0.000000,
        "64" : 0.000000,
        ">=64" : 0.000000
      },
      "latency_ns" : {
        "2" : 0.000000,
        "4" : 0.000000,
        "10" : 0.000000,
        "20" : 0.000000,
        "50" : 0.000000,
        "100" : 0.000000,
        "250" : 0.000000,
        "500" : 0.000000,
        "750" : 0.000000,
        "1000" : 0.000000
      },
      "latency_us" : {
        "2" : 0.010000,
        "4" : 0.000000,
        "10" : 0.010000,
        "20" : 0.427932,
        "50" : 98.821087,
        "100" : 0.075149,
        "250" : 0.010000,
        "500" : 0.010000,
        "750" : 0.010000,
        "1000" : 0.013475
      },
      "latency_ms" : {
        "2" : 0.086396,
        "4" : 0.189678,
        "10" : 0.369825,
        "20" : 0.000000,
        "50" : 0.000000,
        "100" : 0.000000,
        "250" : 0.000000,
        "500" : 0.000000,
        "750" : 0.000000,
        "1000" : 0.000000,
        "2000" : 0.000000,
        ">=2000" : 0.000000
      },
      "latency_depth" : 8,
      "latency_target" : 0,
      "latency_percentile" : 100.000000,
      "latency_window" : 0
    }
  ]
}
