{
  "fio version" : "fio-3.26-38-g3277",
  "timestamp" : 1622527374,
  "timestamp_ms" : 1622527374512,
  "time" : "Tue Jun  1 06:02:54 2021",
  "global options" : {
    "directory" : "/test-volume",
    "bs" : "1024",
    "fallocate" : "none",
    "runtime" : "30",
    "time_based" : "1",
    "ioengine" : "libaio",
    "iodepth" : "8",
    "direct" : "0",
    "buffered" : "1",
    "invalidate" : "1",
    "ramp_time" : "0",
    "thread" : "0",
    "numjobs" : "2",
    "group_reporting" : "1",
    "filesize" : "2G",
    "size" : "2G",
    "filename_format" : "$jobnum.dat"
  },
  "jobs" : [
    {
      "jobname" : "fio-job",
      "groupid" : 0,
      "error" : 0,
      "eta" : 0,
      "elapsed" : 31,
      "job options" : {
        "rw" : "read"
      },
      "read" : {
        "io_bytes" : 19273723904,
        "io_kbytes" : 18821996,
        "bw_bytes" : 642393224,
        "bw" : 627337,
        "iops" : 627337.132953,
        "runtime" : 30003,
        "total_ios" : 18821996,
        "short_ios" : 0,
        "drop_ios" : 0,
        "slat_ns" : {
          "min" : 712,
          "max" : 8029985,
          "mean" : 1779.595711,
          "stddev" : 58323.115809,
          "N" : 18821996
        },
        "clat_ns" : {
          "min" : 1083,
          "max" : 8062734,
          "mean" : 22954.892805,
          "stddev" : 208110.031276,
          "N" : 18821996,
          "percentile" : {
            "1.000000" : 10688,
            "5.000000" : 10688,
            "10.000000" : 10816,
            "20.000000" : 10816,
            "30.000000" : 10944,
            "40.000000" : 11072,
            "50.000000" : 11072,
            "60.000000" : 11200,
            "70.000000" : 11328,
            "80.000000" : 11328,
            "90.000000" : 11584,
            "95.000000" : 11968,
            "99.000000" : 19072,
            "99.500000" : 27520,
            "99.900000" : 4046848,
            "99.950000" : 4046848,
            "99.990000" : 5144576
          },
          "bins" : {
            "1080" : 1,
            "2544" : 1,
            "2928" : 1,
            "3984" : 1,
            "5536" : 1,
            "7264" : 1,
            "8768" : 1,
            "10304" : 3,
            "10432" : 575,
            "10560" : 78111,
            "10688" : 1095525,
            "10816" : 3053114,
            "10944" : 2879946,
            "11072" : 2976618,
            "11200" : 3058602,
            "11328" : 2139827,
            "11456" : 1260501,
            "11584" : 717910,
            "11712" : 398446,
            "11840" : 213329,
            "11968" : 109724,
            "12096" : 56428,
            "12224" : 30641,
            "12352" : 18846,
            "12480" : 12960,
            "12608" : 9660,
            "12736" : 7871,
            "12864" : 7075,
            "12992" : 6530,
            "13120" : 6090,
            "13248" : 5678,
            "13376" : 5589,
            "13504" : 5712,
            "13632" : 5701,
            "13760" : 5668,
            "13888" : 5607,
            "14016" : 5572,
            "14144" : 5511,
            "14272" : 5439,
            "14400" : 5472,
            "14528" : 5452,
            "14656" : 5260,
            "14784" : 5466,
            "14912" : 5550,
            "15040" : 5746,
            "15168" : 6033,
            "15296" : 6499,
            "15424" : 6881,
            "15552" : 7701,
            "15680" : 8741,
            "15808" : 10421,
            "15936" : 12258,
            "16064" : 13700,
            "16192" : 14986,
            "16320" : 16443,
            "16512" : 38483,
            "16768" : 48017,
            "17024" : 44533,
            "17280" : 37244,
            "17536" : 31505,
            "17792" : 26559,
            "18048" : 23108,
            "18304" : 20514,
            "18560" : 18915,
            "18816" : 16626,
            "19072" : 14681,
            "19328" : 13540,
            "19584" : 11802,
            "19840" : 10577,
            "20096" : 8763,
            "20352" : 6844,
            "20608" : 5198,
            "20864" : 3880,
            "21120" : 2659,
            "21376" : 1849,
            "21632" : 1428,
            "21888" : 999,
            "22144" : 735,
            "22400" : 679,
            "22656" : 618,
            "22912" : 543,
            "23168" : 545,
            "23424" : 563,
            "23680" : 538,
            "23936" : 573,
            "24192" : 601,
            "24448" : 607,
            "24704" : 684,
            "24960" : 698,
            "25216" : 694,
            "25472" : 860,
            "25728" : 838,
            "25984" : 893,
            "26240" : 858,
            "26496" : 798,
            "26752" : 729,
            "27008" : 706,
            "27264" : 733,
            "27520" : 672,
            "27776" : 738,
            "28032" : 685,
            "28288" : 662,
            "28544" : 632,
            "28800" : 682,
            "29056" : 582,
            "29312" : 564,
            "29568" : 517,
            "29824" : 494,
            "30080" : 586,
            "30336" : 602,
            "30592" : 581,
            "30848" : 635,
            "31104" : 703,
            "31360" : 868,
            "31616" : 973,
            "31872" : 1098,
            "32128" : 1192,
            "32384" : 1214,
            "32640" : 1115,
            "33024" : 2052,
            "33536" : 1472,
            "34048" : 962,
            "34560" : 625,
            "35072" : 371,
            "35584" : 256,
            "36096" : 185,
            "36608" : 162,
            "37120" : 163,
            "37632" : 185,
            "38144" : 129,
            "38656" : 166,
            "39168" : 146,
            "39680" : 146,
            "40192" : 131,
            "40704" : 109,
            "41216" : 88,
            "41728" : 88,
            "42240" : 68,
            "42752" : 55,
            "43264" : 67,
            "43776" : 45,
            "44288" : 61,
            "44800" : 79,
            "45312" : 109,
            "45824" : 60,
            "46336" : 67,
            "46848" : 90,
            "47360" : 78,
            "47872" : 92,
            "48384" : 79,
            "48896" : 63,
            "49408" : 120,
            "49920" : 109,
            "50432" : 98,
            "50944" : 82,
            "51456" : 68,
            "51968" : 90,
            "52480" : 77,
            "52992" : 98,
            "53504" : 118,
            "54016" : 82,
            "54528" : 84,
            "55040" : 73,
            "55552" : 93,
            "56064" : 111,
            "56576" : 127,
            "57088" : 111,
            "57600" : 160,
            "58112" : 147,
            "58624" : 207,
            "59136" : 174,
            "59648" : 199,
            "60160" : 255,
            "60672" : 174,
            "61184" : 177,
            "61696" : 171,
            "62208" : 152,
            "62720" : 78,
            "63232" : 63,
            "63744" : 79,
            "64256" : 51,
            "64768" : 61,
            "65280" : 82,
            "66048" : 84,
            "67072" : 114,
            "68096" : 89,
            "69120" : 71,
            "70144" : 72,
            "71168" : 40,
            "72192" : 66,
            "73216" : 34,
            "74240" : 59,
            "75264" : 42,
            "76288" : 31,
            "77312" : 19,
            "78336" : 34,
            "79360" : 14,
            "80384" : 9,
            "81408" : 33,
            "82432" : 20,
            "83456" : 14,
            "84480" : 6,
            "85504" : 4,
            "89600" : 2,
            "90624" : 2,
            "91648" : 5,
            "92672" : 5,
            "93696" : 6,
            "94720" : 18,
            "95744" : 11,
            "96768" : 9,
            "97792" : 2,
            "98816" : 4,
            "99840" : 9,
            "100864" : 7,
            "101888" : 5,
            "102912" : 13,
            "103936" : 24,
            "104960" : 4,
            "105984" : 20,
            "107008" : 15,
            "108032" : 3,
            "109056" : 7,
            "110080" : 4,
            "111104" : 10,
            "112128" : 8,
            "113152" : 3,
            "114176" : 12,
            "115200" : 7,
            "116224" : 5,
            "117248" : 2,
            "118272" : 6,
            "119296" : 13,
            "120320" : 12,
            "121344" : 20,
            "122368" : 11,
            "123392" : 4,
            "124416" : 14,
            "125440" : 5,
            "126464" : 24,
            "127488" : 7,
            "128512" : 13,
            "129536" : 7,
            "130560" : 7,
            "132096" : 10,
            "134144" : 1,
            "136192" : 6,
            "179200" : 3,
            "181248" : 5,
            "183296" : 1,
            "185344" : 11,
            "187392" : 6,
            "189440" : 6,
            "191488" : 1,
            "193536" : 4,
            "207872" : 1,
            "209920" : 1,
            "218112" : 1,
            "220160" : 7,
            "222208" : 2,
            "240640" : 2,
            "242688" : 8,
            "244736" : 21,
            "246784" : 3,
            "248832" : 15,
            "250880" : 29,
            "252928" : 16,
            "254976" : 16,
            "257024" : 15,
            "259072" : 14,
            "261120" : 13,
            "264192" : 13,
            "276480" : 15,
            "280576" : 6,
            "284672" : 7,
            "288768" : 13,
            "292864" : 5,
            "296960" : 3,
            "301056" : 2,
            "305152" : 5,
            "317440" : 7,
            "321536" : 1,
            "325632" : 13,
            "337920" : 7,
            "346112" : 1,
            "350208" : 8,
            "354304" : 7,
            "358400" : 13,
            "362496" : 1,
            "366592" : 6,
            "370688" : 7,
            "374784" : 9,
            "382976" : 1,
            "387072" : 13,
            "391168" : 1,
            "395264" : 4,
            "399360" : 2,
            "403456" : 5,
            "423936" : 2,
            "428032" : 5,
            "432128" : 1,
            "436224" : 6,
            "440320" : 1,
            "444416" : 7,
            "452608" : 2,
            "456704" : 12,
            "460800" : 18,
            "464896" : 19,
            "468992" : 2,
            "473088" : 14,
            "477184" : 7,
            "481280" : 7,
            "485376" : 2,
            "489472" : 20,
            "493568" : 6,
            "497664" : 2,
            "501760" : 13,
            "505856" : 6,
            "509952" : 3,
            "514048" : 13,
            "518144" : 6,
            "522240" : 6,
            "536576" : 1,
            "544768" : 23,
            "552960" : 19,
            "561152" : 23,
            "569344" : 13,
            "577536" : 13,
            "585728" : 7,
            "593920" : 9,
            "602112" : 29,
            "610304" : 34,
            "618496" : 5,
            "626688" : 24,
            "634880" : 22,
            "643072" : 14,
            "651264" : 16,
            "659456" : 37,
            "667648" : 14,
            "675840" : 21,
            "684032" : 43,
            "692224" : 32,
            "700416" : 60,
            "708608" : 81,
            "716800" : 34,
            "724992" : 43,
            "733184" : 45,
            "741376" : 23,
            "749568" : 38,
            "757760" : 15,
            "765952" : 25,
            "774144" : 70,
            "782336" : 53,
            "790528" : 34,
            "798720" : 45,
            "806912" : 34,
            "815104" : 36,
            "823296" : 23,
            "831488" : 76,
            "839680" : 48,
            "847872" : 79,
            "856064" : 23,
            "864256" : 23,
            "872448" : 39,
            "880640" : 38,
            "888832" : 17,
            "897024" : 67,
            "905216" : 24,
            "913408" : 61,
            "921600" : 55,
            "929792" : 40,
            "937984" : 30,
            "946176" : 68,
            "954368" : 70,
            "962560" : 55,
            "970752" : 44,
            "978944" : 26,
            "987136" : 55,
            "995328" : 76,
            "1003520" : 45,
            "1011712" : 60,
            "1019904" : 51,
            "1028096" : 4,
            "1036288" : 40,
            "1044480" : 41,
            "1056768" : 76,
            "1073152" : 85,
            "1089536" : 109,
            "1105920" : 99,
            "1122304" : 62,
            "1138688" : 111,
            "1155072" : 109,
            "1171456" : 73,
            "1187840" : 77,
            "1204224" : 108,
            "1220608" : 98,
            "1236992" : 91,
            "1253376" : 121,
            "1269760" : 116,
            "1286144" : 97,
            "1302528" : 95,
            "1318912" : 120,
            "1335296" : 81,
            "1351680" : 100,
            "1368064" : 90,
            "1384448" : 57,
            "1400832" : 108,
            "1417216" : 88,
            "1433600" : 109,
            "1449984" : 114,
            "1466368" : 98,
            "1482752" : 114,
            "1499136" : 141,
            "1515520" : 108,
            "1531904" : 116,
            "1548288" : 182,
            "1564672" : 187,
            "1581056" : 173,
            "1597440" : 156,
            "1613824" : 116,
            "1630208" : 145,
            "1646592" : 200,
            "1662976" : 165,
            "1679360" : 208,
            "1695744" : 103,
            "1712128" : 127,
            "1728512" : 208,
            "1744896" : 184,
            "1761280" : 155,
            "1777664" : 177,
            "1794048" : 136,
            "1810432" : 194,
            "1826816" : 135,
            "1843200" : 134,
            "1859584" : 204,
            "1875968" : 276,
            "1892352" : 193,
            "1908736" : 158,
            "1925120" : 124,
            "1941504" : 145,
            "1957888" : 224,
            "1974272" : 177,
            "1990656" : 197,
            "2007040" : 180,
            "2023424" : 156,
            "2039808" : 175,
            "2056192" : 134,
            "2072576" : 184,
            "2088960" : 179,
            "2113536" : 378,
            "2146304" : 394,
            "2179072" : 305,
            "2211840" : 346,
            "2244608" : 428,
            "2277376" : 344,
            "2310144" : 353,
            "2342912" : 374,
            "2375680" : 360,
            "2408448" : 230,
            "2441216" : 368,
            "2473984" : 375,
            "2506752" : 295,
            "2539520" : 434,
            "2572288" : 349,
            "2605056" : 323,
            "2637824" : 384,
            "2670592" : 328,
            "2703360" : 356,
            "2736128" : 286,
            "2768896" : 340,
            "2801664" : 312,
            "2834432" : 424,
            "2867200" : 425,
            "2899968" : 248,
            "2932736" : 368,
            "2965504" : 322,
            "2998272" : 385,
            "3031040" : 277,
            "3063808" : 311,
            "3096576" : 477,
            "3129344" : 390,
            "3162112" : 353,
            "3194880" : 336,
            "3227648" : 283,
            "3260416" : 383,
            "3293184" : 318,
            "3325952" : 307,
            "3358720" : 335,
            "3391488" : 378,
            "3424256" : 297,
            "3457024" : 209,
            "3489792" : 296,
            "3522560" : 231,
            "3555328" : 183,
            "3588096" : 303,
            "3620864" : 126,
            "3653632" : 242,
            "3686400" : 232,
            "3719168" : 239,
            "3751936" : 141,
            "3784704" : 177,
            "3817472" : 220,
            "3850240" : 209,
            "3883008" : 179,
            "3915776" : 174,
            "3948544" : 148,
            "3981312" : 187,
            "4014080" : 2103,
            "4046848" : 25384,
            "4079616" : 561,
            "4112384" : 222,
            "4145152" : 184,
            "4177920" : 143,
            "4227072" : 336,
            "4292608" : 367,
            "4358144" : 306,
            "4423680" : 376,
            "4489216" : 364,
            "4554752" : 325,
            "4620288" : 455,
            "4685824" : 359,
            "4751360" : 364,
            "4816896" : 365,
            "4882432" : 325,
            "4947968" : 355,
            "5013504" : 356,
            "5079040" : 299,
            "5144576" : 284,
            "5210112" : 293,
            "5275648" : 390,
            "5341184" : 288,
            "5406720" : 284,
            "5472256" : 189,
            "5537792" : 151,
            "5603328" : 93,
            "5668864" : 38,
            "5734400" : 29,
            "5799936" : 21,
            "5865472" : 14,
            "5931008" : 14,
            "5996544" : 14,
            "8028160" : 44,
            "8093696" : 1
          }
        },
        "lat_ns" : {
          "min" : 1940,
          "max" : 8065020,
          "mean" : 24895.670938,
          "stddev" : 216706.519059,
          "N" : 18821996
        },
        "bw_min" : 577628,
        "bw_max" : 636770,
        "bw_agg" : 100.000000,
        "bw_mean" : 627549.559322,
        "bw_dev" : 4017.961860,
        "bw_samples" : 118,
        "iops_min" : 577628,
        "iops_max" : 636770,
        "iops_mean" : 627549.559322,
        "iops_stddev" : 4017.961860,
        "iops_samples" : 118
      },
      "write" : {
        "io_bytes" : 0,
        "io_kbytes" : 0,
        "bw_bytes" : 0,
        "bw" : 0,
        "iops" : 0.000000,
        "runtime" : 0,
        "total_ios" : 0,
        "short_ios" : 0,
        "drop_ios" : 0,
        "slat_ns" : {
          "min" : 0,
          "max" : 0,
          "mean" : 0.000000,
          "stddev" : 0.000000,
          "N" : 0
        },
        "clat_ns" : {
          "min" : 0,
          "max" : 0,
          "mean" : 0.000000,
          "stddev" : 0.000000,
          "N" : 0
        },
        "lat_ns" : {
          "min" : 0,
          "max" : 0,
          "mean" : 0.000000,
          "stddev" : 0.000000,
          "N" : 0
        },
        "bw_min" : 0,
        "bw_max" : 0,
        "bw_agg" : 0.000000,
        "bw_mean" : 0.000000,
        "bw_dev" : 0.000000,
        "bw_samples" : 0,
        "iops_min" : 0,
        "iops_max" : 0,
        "iops_mean" : 0.000000,
        "iops_stddev" : 0.000000,
        "iops_samples" : 0
      },
      "trim" : {
        "io_bytes" : 0,
        "io_kbytes" : 0,
        "bw_bytes" : 0,
        "bw" : 0,
        "iops" : 0.000000,
        "runtime" : 0,
        "total_ios" : 0,
        "short_ios" : 0,
        "drop_ios" : 0,
        "slat_ns" : {
          "min" : 0,
          "max" : 0,
          "mean" : 0.000000,
          "stddev" : 0.000000,
          "N" : 0
        },
        "clat_ns" : {
          "min" : 0,
          "max" : 0,
          "mean" : 0.000000,
          "stddev" : 0.000000,
          "N" : 0
        },
        "lat_ns" : {
          "min" : 0,
          "max" : 0,
          "mean" : 0.000000,
          "stddev" : 0.000000,
          "N" : 0
        },
        "bw_min" : 0,
        "bw_max" : 0,
        "bw_agg" : 0.000000,
        "bw_mean" : 0.000000,
        "bw_dev" : 0.000000,
        "bw_samples" : 0,
        "iops_min" : 0,
        "iops_max" : 0,
        "iops_mean" : 0.000000,
        "iops_stddev" : 0.000000,
        "iops_samples" : 0
      },
      "sync" : {
        "total_ios" : 0,
        "lat_ns" : {
          "min" : 0,
          "max" : 0,
          "mean" : 0.000000,
          "stddev" : 0.000000,
          "N" : 0
        }
      },
      "job_runtime" : 60002,
      "usr_cpu" : 20.522649,
      "sys_cpu" : 29.085697,
      "ctx" : 14071,
      "majf" : 0,
      "minf" : 32,
      "iodepth_level" : {
        "1" : 0.100000,
        "2" : 0.100000,
        "4" : 0.100000,
        "8" : 99.999926,
        "16" : 0.000000,
        "32" : 0.000000,
        ">=64" : 0.000000
      },
      "iodepth_submit" : {
        "0" : 0.000000,
        "4" : 100.000000,
        "8" : 0.000000,
        "16" : 0.000000,
        "32" : 0.000000,
        "64" : 0.000000,
        ">=64" : 0.000000
      },
      "iodepth_complete" : {
        "0" : 0.000000,
        "4" : 99.999989,
        "8" : 0.100000,
        "16" : 0.000000,
        "32" : 0.000000,
        "64" : 0.000000,
        ">=64" : 0.000000
      },
      "latency_ns" : {
        "2" : 0.000000,
        "4" : 0.000000,
        "10" : 0.000000,
        "20" : 0.000000,
        "50" : 0.000000,
        "100" : 0.000000,
        "250" : 0.000000,
        "500" : 0.000000,
        "750" : 0.000000,
        "1000" : 0.000000
      },
      "latency_us" : {
        "2" : 0.010000,
        "4" : 0.010000,
        "10" : 0.010000,
        "20" : 99.259972,
        "50" : 0.368595,
        "100" : 0.023866,
        "250" : 0.010000,
        "500" : 0.010000,
        "750" : 0.010000,
        "1000" : 0.010000
      },
      "latency_ms" : {
        "2" : 0.042530,
        "4" : 0.099835,
        "10" : 0.189555,
        "20" : 0.000000,
        "50" : 0.000000,
        "100" : 0.000000,
        "250" : 0.000000,
        "500" : 0.000000,
        "750" : 0.000000,
        "1000" : 0.000000,
        "2000" : 0.000000,
        ">=2000" : 0.000000
      },
      "latency_depth" : 8,
      "latency_target" : 0,
      "latency_percentile" : 100.000000,
      "latency_window" : 0
    }
  ]
}
