{
  "fio version" : "fio-3.26-38-g3277",
  "timestamp" : 1622521917,
  "timestamp_ms" : 1622521917457,
  "time" : "Tue Jun  1 04:31:57 2021",
  "global options" : {
    "directory" : "/test-volume",
    "bs" : "512",
    "fallocate" : "none",
    "runtime" : "30",
    "time_based" : "1",
    "ioengine" : "libaio",
    "iodepth" : "8",
    "direct" : "0",
    "buffered" : "1",
    "invalidate" : "1",
    "ramp_time" : "0",
    "thread" : "0",
    "numjobs" : "2",
    "group_reporting" : "1",
    "filesize" : "2G",
    "size" : "2G",
    "filename_format" : "$jobnum.dat"
  },
  "jobs" : [
    {
      "jobname" : "fio-job",
      "groupid" : 0,
      "error" : 0,
      "eta" : 0,
      "elapsed" : 31,
      "job options" : {
        "rw" : "read"
      },
      "read" : {
        "io_bytes" : 10310546944,
        "io_kbytes" : 10068893,
        "bw_bytes" : 343673442,
        "bw" : 335618,
        "iops" : 671237.192094,
        "runtime" : 30001,
        "total_ios" : 20137787,
        "short_ios" : 0,
        "drop_ios" : 0,
        "slat_ns" : {
          "min" : 617,
          "max" : 4604860,
          "mean" : 1621.358429,
          "stddev" : 25191.313018,
          "N" : 20137787
        },
        "clat_ns" : {
          "min" : 1019,
          "max" : 320247688,
          "mean" : 21477.991089,
          "stddev" : 387361.013794,
          "N" : 20137787,
          "percentile" : {
            "1.000000" : 9280,
            "5.000000" : 9408,
            "10.000000" : 9408,
            "20.000000" : 9536,
            "30.000000" : 9664,
            "40.000000" : 9664,
            "50.000000" : 9792,
            "60.000000" : 9792,
            "70.000000" : 9792,
            "80.000000" : 9920,
            "90.000000" : 10048,
            "95.000000" : 12352,
            "99.000000" : 749568,
            "99.500000" : 765952,
            "99.900000" : 937984,
            "99.950000" : 1073152,
            "99.990000" : 1318912
          },
          "bins" : {
            "1020" : 1,
            "1224" : 1,
            "2416" : 1,
            "2480" : 1,
            "3696" : 1,
            "3760" : 1,
            "5088" : 2,
            "6432" : 1,
            "6496" : 1,
            "7136" : 1,
            "7712" : 1,
            "7776" : 1,
            "9024" : 36,
            "9152" : 11419,
            "9280" : 359560,
            "9408" : 1825547,
            "9536" : 2536300,
            "9664" : 4549029,
            "9792" : 5923498,
            "9920" : 2731597,
            "10048" : 737155,
            "10176" : 264428,
            "10304" : 95989,
            "10432" : 31375,
            "10560" : 14547,
            "10688" : 8137,
            "10816" : 5574,
            "10944" : 4392,
            "11072" : 3823,
            "11200" : 3611,
            "11328" : 3860,
            "11456" : 3694,
            "11584" : 3342,
            "11712" : 2955,
            "11840" : 2759,
            "11968" : 2627,
            "12096" : 2444,
            "12224" : 2385,
            "12352" : 2342,
            "12480" : 2419,
            "12608" : 2293,
            "12736" : 2412,
            "12864" : 2389,
            "12992" : 2328,
            "13120" : 2578,
            "13248" : 2780,
            "13376" : 3329,
            "13504" : 3993,
            "13632" : 5295,
            "13760" : 6715,
            "13888" : 8743,
            "14016" : 11617,
            "14144" : 14893,
            "14272" : 17337,
            "14400" : 17458,
            "14528" : 16803,
            "14656" : 15497,
            "14784" : 14004,
            "14912" : 13771,
            "15040" : 13537,
            "15168" : 12990,
            "15296" : 12110,
            "15424" : 10920,
            "15552" : 10033,
            "15680" : 9299,
            "15808" : 8592,
            "15936" : 7998,
            "16064" : 7700,
            "16192" : 7313,
            "16320" : 7368,
            "16512" : 16264,
            "16768" : 20086,
            "17024" : 20428,
            "17280" : 15901,
            "17536" : 11307,
            "17792" : 7996,
            "18048" : 5237,
            "18304" : 3626,
            "18560" : 2152,
            "18816" : 1334,
            "19072" : 956,
            "19328" : 615,
            "19584" : 527,
            "19840" : 517,
            "20096" : 521,
            "20352" : 498,
            "20608" : 501,
            "20864" : 631,
            "21120" : 715,
            "21376" : 1032,
            "21632" : 1580,
            "21888" : 2039,
            "22144" : 2811,
            "22400" : 3472,
            "22656" : 4211,
            "22912" : 4249,
            "23168" : 4363,
            "23424" : 3966,
            "23680" : 3342,
            "23936" : 2906,
            "24192" : 2097,
            "24448" : 1606,
            "24704" : 1170,
            "24960" : 890,
            "25216" : 734,
            "25472" : 705,
            "25728" : 588,
            "25984" : 630,
            "26240" : 519,
            "26496" : 438,
            "26752" : 383,
            "27008" : 315,
            "27264" : 278,
            "27520" : 245,
            "27776" : 236,
            "28032" : 218,
            "28288" : 244,
            "28544" : 233,
            "28800" : 234,
            "29056" : 212,
            "29312" : 198,
            "29568" : 196,
            "29824" : 217,
            "30080" : 215,
            "30336" : 228,
            "30592" : 207,
            "30848" : 204,
            "31104" : 182,
            "31360" : 145,
            "31616" : 110,
            "31872" : 99,
            "32128" : 93,
            "32384" : 70,
            "32640" : 52,
            "33024" : 113,
            "33536" : 124,
            "34048" : 120,
            "34560" : 138,
            "35072" : 120,
            "35584" : 147,
            "36096" : 130,
            "36608" : 101,
            "37120" : 103,
            "37632" : 83,
            "38144" : 93,
            "38656" : 166,
            "39168" : 1386,
            "39680" : 8269,
            "40192" : 22799,
            "40704" : 36147,
            "41216" : 40513,
            "41728" : 37963,
            "42240" : 30856,
            "42752" : 22895,
            "43264" : 16430,
            "43776" : 12951,
            "44288" : 9762,
            "44800" : 7521,
            "45312" : 6116,
            "45824" : 4548,
            "46336" : 3533,
            "46848" : 2861,
            "47360" : 2520,
            "47872" : 2118,
            "48384" : 1728,
            "48896" : 1561,
            "49408" : 1466,
            "49920" : 1289,
            "50432" : 1055,
            "50944" : 925,
            "51456" : 719,
            "51968" : 612,
            "52480" : 483,
            "52992" : 390,
            "53504" : 317,
            "54016" : 314,
            "54528" : 203,
            "55040" : 221,
            "55552" : 195,
            "56064" : 167,
            "56576" : 171,
            "57088" : 158,
            "57600" : 127,
            "58112" : 129,
            "58624" : 138,
            "59136" : 108,
            "59648" : 105,
            "60160" : 79,
            "60672" : 70,
            "61184" : 49,
            "61696" : 55,
            "62208" : 71,
            "62720" : 58,
            "63232" : 48,
            "63744" : 61,
            "64256" : 92,
            "64768" : 80,
            "65280" : 68,
            "66048" : 132,
            "67072" : 120,
            "68096" : 113,
            "69120" : 105,
            "70144" : 81,
            "71168" : 88,
            "72192" : 57,
            "73216" : 53,
            "74240" : 59,
            "75264" : 38,
            "76288" : 30,
            "77312" : 47,
            "78336" : 34,
            "79360" : 67,
            "80384" : 96,
            "81408" : 51,
            "82432" : 68,
            "83456" : 96,
            "84480" : 94,
            "85504" : 66,
            "86528" : 63,
            "87552" : 67,
            "88576" : 47,
            "89600" : 54,
            "90624" : 40,
            "91648" : 19,
            "92672" : 22,
            "93696" : 49,
            "94720" : 54,
            "95744" : 41,
            "96768" : 19,
            "97792" : 24,
            "98816" : 25,
            "99840" : 16,
            "100864" : 11,
            "101888" : 17,
            "102912" : 17,
            "103936" : 3,
            "104960" : 12,
            "105984" : 2,
            "107008" : 2,
            "108032" : 1,
            "110080" : 4,
            "111104" : 12,
            "112128" : 15,
            "113152" : 9,
            "114176" : 2,
            "115200" : 9,
            "116224" : 9,
            "117248" : 10,
            "118272" : 13,
            "119296" : 5,
            "120320" : 1,
            "121344" : 5,
            "122368" : 2,
            "123392" : 10,
            "124416" : 9,
            "125440" : 21,
            "126464" : 30,
            "127488" : 23,
            "128512" : 6,
            "129536" : 13,
            "130560" : 8,
            "132096" : 24,
            "134144" : 65,
            "136192" : 44,
            "138240" : 76,
            "140288" : 40,
            "142336" : 53,
            "144384" : 46,
            "146432" : 51,
            "148480" : 5,
            "150528" : 48,
            "152576" : 32,
            "154624" : 60,
            "156672" : 50,
            "158720" : 35,
            "160768" : 31,
            "162816" : 39,
            "164864" : 31,
            "166912" : 13,
            "168960" : 33,
            "171008" : 46,
            "173056" : 37,
            "175104" : 53,
            "177152" : 36,
            "179200" : 41,
            "181248" : 8,
            "183296" : 57,
            "185344" : 22,
            "187392" : 38,
            "189440" : 19,
            "191488" : 27,
            "193536" : 35,
            "195584" : 52,
            "197632" : 54,
            "199680" : 36,
            "201728" : 42,
            "203776" : 30,
            "205824" : 35,
            "207872" : 19,
            "209920" : 43,
            "211968" : 43,
            "214016" : 13,
            "216064" : 40,
            "218112" : 52,
            "220160" : 91,
            "222208" : 26,
            "224256" : 48,
            "226304" : 32,
            "228352" : 31,
            "230400" : 11,
            "232448" : 69,
            "234496" : 42,
            "236544" : 86,
            "238592" : 57,
            "240640" : 37,
            "242688" : 52,
            "244736" : 86,
            "246784" : 42,
            "248832" : 41,
            "250880" : 36,
            "252928" : 71,
            "254976" : 39,
            "257024" : 77,
            "259072" : 71,
            "261120" : 70,
            "264192" : 155,
            "268288" : 112,
            "272384" : 140,
            "276480" : 78,
            "280576" : 171,
            "284672" : 134,
            "288768" : 195,
            "292864" : 196,
            "296960" : 170,
            "301056" : 139,
            "305152" : 119,
            "309248" : 165,
            "313344" : 250,
            "317440" : 131,
            "321536" : 195,
            "325632" : 217,
            "329728" : 139,
            "333824" : 275,
            "337920" : 137,
            "342016" : 198,
            "346112" : 172,
            "350208" : 171,
            "354304" : 194,
            "358400" : 208,
            "362496" : 154,
            "366592" : 227,
            "370688" : 239,
            "374784" : 257,
            "378880" : 250,
            "382976" : 177,
            "387072" : 230,
            "391168" : 173,
            "395264" : 253,
            "399360" : 298,
            "403456" : 322,
            "407552" : 281,
            "411648" : 261,
            "415744" : 299,
            "419840" : 250,
            "423936" : 195,
            "428032" : 280,
            "432128" : 312,
            "436224" : 253,
            "440320" : 286,
            "444416" : 341,
            "448512" : 238,
            "452608" : 404,
            "456704" : 340,
            "460800" : 286,
            "464896" : 324,
            "468992" : 269,
            "473088" : 301,
            "477184" : 318,
            "481280" : 355,
            "485376" : 286,
            "489472" : 280,
            "493568" : 349,
            "497664" : 272,
            "501760" : 248,
            "505856" : 302,
            "509952" : 316,
            "514048" : 405,
            "518144" : 287,
            "522240" : 406,
            "528384" : 841,
            "536576" : 681,
            "544768" : 713,
            "552960" : 599,
            "561152" : 740,
            "569344" : 848,
            "577536" : 685,
            "585728" : 740,
            "593920" : 660,
            "602112" : 699,
            "610304" : 803,
            "618496" : 786,
            "626688" : 734,
            "634880" : 686,
            "643072" : 646,
            "651264" : 590,
            "659456" : 423,
            "667648" : 668,
            "675840" : 1067,
            "684032" : 1044,
            "692224" : 1296,
            "700416" : 1597,
            "708608" : 1784,
            "716800" : 1894,
            "724992" : 3473,
            "733184" : 8214,
            "741376" : 18620,
            "749568" : 37584,
            "757760" : 46400,
            "765952" : 33389,
            "774144" : 21872,
            "782336" : 13738,
            "790528" : 8256,
            "798720" : 6981,
            "806912" : 6223,
            "815104" : 4909,
            "823296" : 3721,
            "831488" : 2695,
            "839680" : 1969,
            "847872" : 1467,
            "856064" : 849,
            "864256" : 708,
            "872448" : 723,
            "880640" : 719,
            "888832" : 675,
            "897024" : 691,
            "905216" : 619,
            "913408" : 800,
            "921600" : 608,
            "929792" : 673,
            "937984" : 629,
            "946176" : 724,
            "954368" : 725,
            "962560" : 631,
            "970752" : 616,
            "978944" : 738,
            "987136" : 653,
            "995328" : 641,
            "1003520" : 603,
            "1011712" : 631,
            "1019904" : 575,
            "1028096" : 431,
            "1036288" : 512,
            "1044480" : 565,
            "1056768" : 975,
            "1073152" : 941,
            "1089536" : 947,
            "1105920" : 793,
            "1122304" : 846,
            "1138688" : 732,
            "1155072" : 707,
            "1171456" : 669,
            "1187840" : 536,
            "1204224" : 420,
            "1220608" : 422,
            "1236992" : 425,
            "1253376" : 349,
            "1269760" : 327,
            "1286144" : 315,
            "1302528" : 310,
            "1318912" : 275,
            "1335296" : 163,
            "1351680" : 151,
            "1368064" : 150,
            "1384448" : 96,
            "1400832" : 105,
            "1417216" : 133,
            "1433600" : 137,
            "1449984" : 115,
            "1466368" : 167,
            "1482752" : 171,
            "1499136" : 140,
            "1515520" : 68,
            "1531904" : 39,
            "1548288" : 10,
            "1564672" : 8,
            "1581056" : 16,
            "1597440" : 26,
            "1613824" : 1,
            "1646592" : 7,
            "1679360" : 4,
            "1695744" : 4,
            "1712128" : 7,
            "1777664" : 1,
            "1794048" : 11,
            "1810432" : 3,
            "1826816" : 4,
            "1843200" : 5,
            "1859584" : 28,
            "1875968" : 8,
            "1892352" : 10,
            "1908736" : 16,
            "1925120" : 2,
            "1941504" : 21,
            "2039808" : 1,
            "2072576" : 13,
            "2088960" : 7,
            "2113536" : 4,
            "2146304" : 3,
            "2179072" : 7,
            "2244608" : 7,
            "2277376" : 7,
            "2310144" : 8,
            "2342912" : 7,
            "2572288" : 7,
            "2867200" : 7,
            "3031040" : 7,
            "3129344" : 7,
            "3293184" : 9,
            "3325952" : 5,
            "3358720" : 1,
            "3391488" : 7,
            "4227072" : 8,
            "4292608" : 6,
            "4620288" : 7,
            "316669952" : 7,
            "320864256" : 21
          }
        },
        "lat_ns" : {
          "min" : 1855,
          "max" : 320248447,
          "mean" : 23216.626846,
          "stddev" : 388221.054705,
          "N" : 20137787
        },
        "bw_min" : 179508,
        "bw_max" : 345811,
        "bw_agg" : 99.967345,
        "bw_mean" : 335509.084746,
        "bw_dev" : 14928.977390,
        "bw_samples" : 118,
        "iops_min" : 359016,
        "iops_max" : 691622,
        "iops_mean" : 671018.169492,
        "iops_stddev" : 29857.954865,
        "iops_samples" : 118
      },
      "write" : {
        "io_bytes" : 0,
        "io_kbytes" : 0,
        "bw_bytes" : 0,
        "bw" : 0,
        "iops" : 0.000000,
        "runtime" : 0,
        "total_ios" : 0,
        "short_ios" : 0,
        "drop_ios" : 0,
        "slat_ns" : {
          "min" : 0,
          "max" : 0,
          "mean" : 0.000000,
          "stddev" : 0.000000,
          "N" : 0
        },
        "clat_ns" : {
          "min" : 0,
          "max" : 0,
          "mean" : 0.000000,
          "stddev" : 0.000000,
          "N" : 0
        },
        "lat_ns" : {
          "min" : 0,
          "max" : 0,
          "mean" : 0.000000,
          "stddev" : 0.000000,
          "N" : 0
        },
        "bw_min" : 0,
        "bw_max" : 0,
        "bw_agg" : 0.000000,
        "bw_mean" : 0.000000,
        "bw_dev" : 0.000000,
        "bw_samples" : 0,
        "iops_min" : 0,
        "iops_max" : 0,
        "iops_mean" : 0.000000,
        "iops_stddev" : 0.000000,
        "iops_samples" : 0
      },
      "trim" : {
        "io_bytes" : 0,
        "io_kbytes" : 0,
        "bw_bytes" : 0,
        "bw" : 0,
        "iops" : 0.000000,
        "runtime" : 0,
        "total_ios" : 0,
        "short_ios" : 0,
        "drop_ios" : 0,
        "slat_ns" : {
          "min" : 0,
          "max" : 0,
          "mean" : 0.000000,
          "stddev" : 0.000000,
          "N" : 0
        },
        "clat_ns" : {
          "min" : 0,
          "max" : 0,
          "mean" : 0.000000,
          "stddev" : 0.000000,
          "N" : 0
        },
        "lat_ns" : {
          "min" : 0,
          "max" : 0,
          "mean" : 0.000000,
          "stddev" : 0.000000,
          "N" : 0
        },
        "bw_min" : 0,
        "bw_max" : 0,
        "bw_agg" : 0.000000,
        "bw_mean" : 0.000000,
        "bw_dev" : 0.000000,
        "bw_samples" : 0,
        "iops_min" : 0,
        "iops_max" : 0,
        "iops_mean" : 0.000000,
        "iops_stddev" : 0.000000,
        "iops_samples" : 0
      },
      "sync" : {
        "total_ios" : 0,
        "lat_ns" : {
          "min" : 0,
          "max" : 0,
          "mean" : 0.000000,
          "stddev" : 0.000000,
          "N" : 0
        }
      },
      "job_runtime" : 60000,
      "usr_cpu" : 19.560000,
      "sys_cpu" : 29.755000,
      "ctx" : 53160,
      "majf" : 0,
      "minf" : 29,
      "iodepth_level" : {
        "1" : 0.100000,
        "2" : 0.100000,
        "4" : 0.100000,
        "8" : 99.999930,
        "16" : 0.000000,
        "32" : 0.000000,
        ">=64" : 0.000000
      },
      "iodepth_submit" : {
        "0" : 0.000000,
        "4" : 100.000000,
        "8" : 0.000000,
        "16" : 0.000000,
        "32" : 0.000000,
        "64" : 0.000000,
        ">=64" : 0.000000
      },
      "iodepth_complete" : {
        "0" : 0.000000,
        "4" : 99.999990,
        "8" : 0.100000,
        "16" : 0.000000,
        "32" : 0.000000,
        "64" : 0.000000,
        ">=64" : 0.000000
      },
      "latency_ns" : {
        "2" : 0.000000,
        "4" : 0.000000,
        "10" : 0.000000,
        "20" : 0.000000,
        "50" : 0.000000,
        "100" : 0.000000,
        "250" : 0.000000,
        "500" : 0.000000,
        "750" : 0.000000,
        "1000" : 0.000000
      },
      "latency_us" : {
        "2" : 0.010000,
        "4" : 0.010000,
        "10" : 89.801580,
        "20" : 7.100636,
        "50" : 1.624761,
        "100" : 0.048317,
        "250" : 0.013413,
        "500" : 0.068448,
        "750" : 0.354547,
        "1000" : 0.912583
      },
      "latency_ms" : {
        "2" : 0.074874,
        "4" : 0.010000,
        "10" : 0.010000,
        "20" : 0.000000,
        "50" : 0.000000,
        "100" : 0.000000,
        "250" : 0.000000,
        "500" : 0.010000,
        "750" : 0.000000,
        "1000" : 0.000000,
        "2000" : 0.000000,
        ">=2000" : 0.000000
      },
      "latency_depth" : 8,
      "latency_target" : 0,
      "latency_percentile" : 100.000000,
      "latency_window" : 0
    }
  ]
}
