{
  "fio version" : "fio-3.26-38-g3277",
  "timestamp" : 1622652767,
  "timestamp_ms" : 1622652767717,
  "time" : "Wed Jun  2 16:52:47 2021",
  "global options" : {
    "directory" : "/test-volume",
    "bs" : "1024",
    "fallocate" : "none",
    "runtime" : "30",
    "time_based" : "1",
    "ioengine" : "libaio",
    "iodepth" : "8",
    "direct" : "0",
    "buffered" : "1",
    "invalidate" : "1",
    "ramp_time" : "0",
    "thread" : "0",
    "numjobs" : "1",
    "group_reporting" : "1",
    "filesize" : "2G",
    "size" : "2G",
    "filename_format" : "$jobnum.dat"
  },
  "jobs" : [
    {
      "jobname" : "fio-job",
      "groupid" : 0,
      "error" : 0,
      "eta" : 0,
      "elapsed" : 31,
      "job options" : {
        "rw" : "write"
      },
      "read" : {
        "io_bytes" : 0,
        "io_kbytes" : 0,
        "bw_bytes" : 0,
        "bw" : 0,
        "iops" : 0.000000,
        "runtime" : 0,
        "total_ios" : 0,
        "short_ios" : 0,
        "drop_ios" : 0,
        "slat_ns" : {
          "min" : 0,
          "max" : 0,
          "mean" : 0.000000,
          "stddev" : 0.000000,
          "N" : 0
        },
        "clat_ns" : {
          "min" : 0,
          "max" : 0,
          "mean" : 0.000000,
          "stddev" : 0.000000,
          "N" : 0
        },
        "lat_ns" : {
          "min" : 0,
          "max" : 0,
          "mean" : 0.000000,
          "stddev" : 0.000000,
          "N" : 0
        },
        "bw_min" : 0,
        "bw_max" : 0,
        "bw_agg" : 0.000000,
        "bw_mean" : 0.000000,
        "bw_dev" : 0.000000,
        "bw_samples" : 0,
        "iops_min" : 0,
        "iops_max" : 0,
        "iops_mean" : 0.000000,
        "iops_stddev" : 0.000000,
        "iops_samples" : 0
      },
      "write" : {
        "io_bytes" : 2744787968,
        "io_kbytes" : 2680457,
        "bw_bytes" : 91489882,
        "bw" : 89345,
        "iops" : 89345.588480,
        "runtime" : 30001,
        "total_ios" : 2680457,
        "short_ios" : 0,
        "drop_ios" : 0,
        "slat_ns" : {
          "min" : 976,
          "max" : 832263,
          "mean" : 8438.479501,
          "stddev" : 30198.688141,
          "N" : 2680457
        },
        "clat_ns" : {
          "min" : 1573,
          "max" : 5377412003,
          "mean" : 78732.359517,
          "stddev" : 8690329.548048,
          "N" : 2680457,
          "percentile" : {
            "1.000000" : 13248,
            "5.000000" : 13248,
            "10.000000" : 13376,
            "20.000000" : 14016,
            "30.000000" : 14144,
            "40.000000" : 14144,
            "50.000000" : 14272,
            "60.000000" : 14528,
            "70.000000" : 15296,
            "80.000000" : 130560,
            "90.000000" : 252928,
            "95.000000" : 313344,
            "99.000000" : 350208,
            "99.500000" : 366592,
            "99.900000" : 403456,
            "99.950000" : 419840,
            "99.990000" : 456704
          },
          "bins" : {
            "1576" : 1,
            "12992" : 152,
            "13120" : 15021,
            "13248" : 142845,
            "13376" : 184905,
            "13504" : 58429,
            "13632" : 28120,
            "13760" : 24637,
            "13888" : 52374,
            "14016" : 280977,
            "14144" : 397769,
            "14272" : 197887,
            "14400" : 138422,
            "14528" : 138417,
            "14656" : 85144,
            "14784" : 49111,
            "14912" : 28268,
            "15040" : 15854,
            "15168" : 22490,
            "15296" : 50233,
            "15424" : 50420,
            "15552" : 29012,
            "15680" : 22645,
            "15808" : 18426,
            "15936" : 10366,
            "16064" : 6298,
            "16192" : 4104,
            "16320" : 2242,
            "16512" : 2486,
            "16768" : 2607,
            "17024" : 3581,
            "17280" : 2400,
            "17536" : 3914,
            "17792" : 6438,
            "18048" : 4645,
            "18304" : 3346,
            "18560" : 1924,
            "18816" : 1600,
            "19072" : 1697,
            "19328" : 1220,
            "19584" : 1034,
            "19840" : 788,
            "20096" : 664,
            "20352" : 628,
            "20608" : 548,
            "20864" : 456,
            "21120" : 408,
            "21376" : 387,
            "21632" : 403,
            "21888" : 288,
            "22144" : 240,
            "22400" : 194,
            "22656" : 114,
            "22912" : 82,
            "23168" : 48,
            "23424" : 69,
            "23680" : 63,
            "23936" : 56,
            "24192" : 46,
            "24448" : 23,
            "24704" : 17,
            "24960" : 18,
            "25216" : 6,
            "25472" : 11,
            "25728" : 4,
            "25984" : 16,
            "26240" : 6,
            "26496" : 8,
            "26752" : 6,
            "27008" : 4,
            "27264" : 3,
            "27520" : 8,
            "27776" : 8,
            "28032" : 5,
            "28288" : 2,
            "28544" : 8,
            "28800" : 5,
            "29056" : 4,
            "29312" : 4,
            "29568" : 6,
            "29824" : 3,
            "30080" : 3,
            "30336" : 3,
            "30592" : 7,
            "30848" : 7,
            "31360" : 2,
            "31616" : 6,
            "44800" : 1,
            "45312" : 1,
            "45824" : 1,
            "46848" : 3,
            "47360" : 3,
            "47872" : 11,
            "48384" : 9,
            "48896" : 3,
            "49408" : 5,
            "49920" : 3,
            "50432" : 4,
            "50944" : 3,
            "51456" : 1,
            "51968" : 1,
            "52480" : 1,
            "52992" : 1,
            "54016" : 1,
            "54528" : 2,
            "55040" : 1,
            "55552" : 1,
            "56064" : 2,
            "57088" : 1,
            "57600" : 3,
            "58112" : 3,
            "58624" : 4,
            "59136" : 1,
            "59648" : 5,
            "60160" : 4,
            "60672" : 5,
            "61184" : 2,
            "61696" : 2,
            "62208" : 1,
            "62720" : 1,
            "63232" : 1,
            "63744" : 1,
            "64768" : 1,
            "65280" : 1,
            "67072" : 1,
            "68096" : 1,
            "70144" : 2,
            "72192" : 1,
            "75264" : 1,
            "76288" : 3,
            "77312" : 2,
            "78336" : 1,
            "79360" : 6,
            "80384" : 14,
            "81408" : 20,
            "82432" : 30,
            "83456" : 14,
            "84480" : 16,
            "85504" : 14,
            "86528" : 9,
            "87552" : 7,
            "88576" : 10,
            "89600" : 6,
            "90624" : 2,
            "91648" : 1,
            "92672" : 4,
            "93696" : 1,
            "94720" : 7,
            "95744" : 2,
            "96768" : 12,
            "97792" : 9,
            "98816" : 6,
            "99840" : 21,
            "100864" : 15,
            "101888" : 6,
            "102912" : 14,
            "103936" : 15,
            "104960" : 4,
            "105984" : 8,
            "107008" : 3,
            "108032" : 3,
            "109056" : 57,
            "110080" : 170,
            "111104" : 332,
            "112128" : 449,
            "113152" : 952,
            "114176" : 1409,
            "115200" : 1734,
            "116224" : 2359,
            "117248" : 2551,
            "118272" : 3349,
            "119296" : 3778,
            "120320" : 4640,
            "121344" : 4480,
            "122368" : 2995,
            "123392" : 2320,
            "124416" : 1899,
            "125440" : 2558,
            "126464" : 2032,
            "127488" : 2141,
            "128512" : 2639,
            "129536" : 2967,
            "130560" : 5155,
            "132096" : 6654,
            "134144" : 4459,
            "136192" : 5047,
            "138240" : 5155,
            "140288" : 4830,
            "142336" : 3716,
            "144384" : 2293,
            "146432" : 1531,
            "148480" : 1251,
            "150528" : 1211,
            "152576" : 1135,
            "154624" : 1209,
            "156672" : 1127,
            "158720" : 1243,
            "160768" : 1834,
            "162816" : 2898,
            "164864" : 3290,
            "166912" : 4719,
            "168960" : 4558,
            "171008" : 5938,
            "173056" : 5817,
            "175104" : 4164,
            "177152" : 3033,
            "179200" : 2363,
            "181248" : 1620,
            "183296" : 1364,
            "185344" : 1375,
            "187392" : 1198,
            "189440" : 1062,
            "191488" : 930,
            "193536" : 751,
            "195584" : 624,
            "197632" : 577,
            "199680" : 527,
            "201728" : 520,
            "203776" : 545,
            "205824" : 886,
            "207872" : 793,
            "209920" : 890,
            "211968" : 1204,
            "214016" : 1823,
            "216064" : 2756,
            "218112" : 4828,
            "220160" : 8377,
            "222208" : 12225,
            "224256" : 14915,
            "226304" : 16033,
            "228352" : 12623,
            "230400" : 10646,
            "232448" : 10644,
            "234496" : 8548,
            "236544" : 6663,
            "238592" : 4563,
            "240640" : 3972,
            "242688" : 4922,
            "244736" : 8121,
            "246784" : 12355,
            "248832" : 9238,
            "250880" : 8159,
            "252928" : 8797,
            "254976" : 9505,
            "257024" : 10088,
            "259072" : 8636,
            "261120" : 7928,
            "264192" : 16545,
            "268288" : 14634,
            "272384" : 9139,
            "276480" : 7272,
            "280576" : 6773,
            "284672" : 6603,
            "288768" : 6789,
            "292864" : 6300,
            "296960" : 5710,
            "301056" : 4842,
            "305152" : 4154,
            "309248" : 5906,
            "313344" : 7519,
            "317440" : 9817,
            "321536" : 14342,
            "325632" : 17964,
            "329728" : 18676,
            "333824" : 14878,
            "337920" : 10553,
            "342016" : 6979,
            "346112" : 5522,
            "350208" : 4494,
            "354304" : 3374,
            "358400" : 3261,
            "362496" : 3405,
            "366592" : 3039,
            "370688" : 2474,
            "374784" : 1916,
            "378880" : 1508,
            "382976" : 1242,
            "387072" : 973,
            "391168" : 797,
            "395264" : 607,
            "399360" : 538,
            "403456" : 439,
            "407552" : 357,
            "411648" : 290,
            "415744" : 212,
            "419840" : 205,
            "423936" : 181,
            "428032" : 152,
            "432128" : 140,
            "436224" : 118,
            "440320" : 104,
            "444416" : 81,
            "448512" : 81,
            "452608" : 68,
            "456704" : 39,
            "460800" : 32,
            "464896" : 28,
            "468992" : 24,
            "473088" : 25,
            "477184" : 16,
            "481280" : 19,
            "485376" : 12,
            "489472" : 11,
            "493568" : 2,
            "497664" : 8,
            "501760" : 8,
            "505856" : 5,
            "509952" : 2,
            "528384" : 6,
            "536576" : 3,
            "561152" : 1,
            "610304" : 1,
            "626688" : 1,
            "667648" : 4,
            "675840" : 2,
            "724992" : 3,
            "733184" : 1,
            "741376" : 5,
            "765952" : 3,
            "782336" : 3,
            "864256" : 1,
            "913408" : 1,
            "921600" : 2,
            "962560" : 1,
            "970752" : 2,
            "978944" : 3,
            "5402263552" : 7
          }
        },
        "lat_ns" : {
          "min" : 14847,
          "max" : 5377413095,
          "mean" : 87258.173719,
          "stddev" : 8690442.351447,
          "N" : 2680457
        },
        "bw_min" : 27966,
        "bw_max" : 505300,
        "bw_agg" : 100.000000,
        "bw_mean" : 108858.612245,
        "bw_dev" : 177109.500214,
        "bw_samples" : 49,
        "iops_min" : 27966,
        "iops_max" : 505300,
        "iops_mean" : 108858.612245,
        "iops_stddev" : 177109.500214,
        "iops_samples" : 49
      },
      "trim" : {
        "io_bytes" : 0,
        "io_kbytes" : 0,
        "bw_bytes" : 0,
        "bw" : 0,
        "iops" : 0.000000,
        "runtime" : 0,
        "total_ios" : 0,
        "short_ios" : 0,
        "drop_ios" : 0,
        "slat_ns" : {
          "min" : 0,
          "max" : 0,
          "mean" : 0.000000,
          "stddev" : 0.000000,
          "N" : 0
        },
        "clat_ns" : {
          "min" : 0,
          "max" : 0,
          "mean" : 0.000000,
          "stddev" : 0.000000,
          "N" : 0
        },
        "lat_ns" : {
          "min" : 0,
          "max" : 0,
          "mean" : 0.000000,
          "stddev" : 0.000000,
          "N" : 0
        },
        "bw_min" : 0,
        "bw_max" : 0,
        "bw_agg" : 0.000000,
        "bw_mean" : 0.000000,
        "bw_dev" : 0.000000,
        "bw_samples" : 0,
        "iops_min" : 0,
        "iops_max" : 0,
        "iops_mean" : 0.000000,
        "iops_stddev" : 0.000000,
        "iops_samples" : 0
      },
      "sync" : {
        "total_ios" : 0,
        "lat_ns" : {
          "min" : 0,
          "max" : 0,
          "mean" : 0.000000,
          "stddev" : 0.000000,
          "N" : 0
        }
      },
      "job_runtime" : 30000,
      "usr_cpu" : 5.816667,
      "sys_cpu" : 17.433333,
      "ctx" : 148016,
      "majf" : 0,
      "minf" : 15,
      "iodepth_level" : {
        "1" : 0.100000,
        "2" : 0.100000,
        "4" : 0.100000,
        "8" : 99.999739,
        "16" : 0.000000,
        "32" : 0.000000,
        ">=64" : 0.000000
      },
      "iodepth_submit" : {
        "0" : 0.000000,
        "4" : 100.000000,
        "8" : 0.000000,
        "16" : 0.000000,
        "32" : 0.000000,
        "64" : 0.000000,
        ">=64" : 0.000000
      },
      "iodepth_complete" : {
        "0" : 0.000000,
        "4" : 99.999963,
        "8" : 0.100000,
        "16" : 0.000000,
        "32" : 0.000000,
        "64" : 0.000000,
        ">=64" : 0.000000
      },
      "latency_ns" : {
        "2" : 0.000000,
        "4" : 0.000000,
        "10" : 0.000000,
        "20" : 0.000000,
        "50" : 0.000000,
        "100" : 0.000000,
        "250" : 0.000000,
        "500" : 0.000000,
        "750" : 0.000000,
        "1000" : 0.000000
      },
      "latency_us" : {
        "2" : 0.010000,
        "4" : 0.000000,
        "10" : 0.000000,
        "20" : 78.058779,
        "50" : 0.180977,
        "100" : 0.010073,
        "250" : 11.160933,
        "500" : 10.586777,
        "750" : 0.010000,
        "1000" : 0.010000
      },
      "latency_ms" : {
        "2" : 0.000000,
        "4" : 0.000000,
        "10" : 0.000000,
        "20" : 0.000000,
        "50" : 0.000000,
        "100" : 0.000000,
        "250" : 0.000000,
        "500" : 0.000000,
        "750" : 0.000000,
        "1000" : 0.000000,
        "2000" : 0.000000,
        ">=2000" : 0.010000
      },
      "latency_depth" : 8,
      "latency_target" : 0,
      "latency_percentile" : 100.000000,
      "latency_window" : 0
    }
  ],
  "disk_util" : [
    {
      "name" : "dm-0",
      "read_ios" : 299951,
      "write_ios" : 1959,
      "read_merges" : 0,
      "write_merges" : 0,
      "read_ticks" : 42078,
      "write_ticks" : 34332,
      "in_queue" : 76410,
      "util" : 96.350170,
      "aggr_read_ios" : 301671,
      "aggr_write_ios" : 4306,
      "aggr_read_merges" : 0,
      "aggr_write_merge" : 5,
      "aggr_read_ticks" : 42861,
      "aggr_write_ticks" : 56965,
      "aggr_in_queue" : 59255,
      "aggr_util" : 99.053376
    },
    {
      "name" : "sda",
      "read_ios" : 301671,
      "write_ios" : 4306,
      "read_merges" : 0,
      "write_merges" : 5,
      "read_ticks" : 42861,
      "write_ticks" : 56965,
      "in_queue" : 59255,
      "util" : 99.053376
    }
  ]
}
