{
  "fio version" : "fio-3.26-38-g3277",
  "timestamp" : 1622621836,
  "timestamp_ms" : 1622621836858,
  "time" : "Wed Jun  2 08:17:16 2021",
  "global options" : {
    "directory" : "/tmp/test-volume",
    "bs" : "1024",
    "fallocate" : "none",
    "runtime" : "30",
    "time_based" : "1",
    "ioengine" : "libaio",
    "iodepth" : "8",
    "direct" : "0",
    "buffered" : "1",
    "invalidate" : "1",
    "ramp_time" : "0",
    "thread" : "0",
    "numjobs" : "1",
    "group_reporting" : "1",
    "filesize" : "2G",
    "size" : "2G",
    "filename_format" : "$jobnum.dat"
  },
  "jobs" : [
    {
      "jobname" : "fio-job",
      "groupid" : 0,
      "error" : 0,
      "eta" : 0,
      "elapsed" : 31,
      "job options" : {
        "rw" : "write"
      },
      "read" : {
        "io_bytes" : 0,
        "io_kbytes" : 0,
        "bw_bytes" : 0,
        "bw" : 0,
        "iops" : 0.000000,
        "runtime" : 0,
        "total_ios" : 0,
        "short_ios" : 0,
        "drop_ios" : 0,
        "slat_ns" : {
          "min" : 0,
          "max" : 0,
          "mean" : 0.000000,
          "stddev" : 0.000000,
          "N" : 0
        },
        "clat_ns" : {
          "min" : 0,
          "max" : 0,
          "mean" : 0.000000,
          "stddev" : 0.000000,
          "N" : 0
        },
        "lat_ns" : {
          "min" : 0,
          "max" : 0,
          "mean" : 0.000000,
          "stddev" : 0.000000,
          "N" : 0
        },
        "bw_min" : 0,
        "bw_max" : 0,
        "bw_agg" : 0.000000,
        "bw_mean" : 0.000000,
        "bw_dev" : 0.000000,
        "bw_samples" : 0,
        "iops_min" : 0,
        "iops_max" : 0,
        "iops_mean" : 0.000000,
        "iops_stddev" : 0.000000,
        "iops_samples" : 0
      },
      "write" : {
        "io_bytes" : 1138973696,
        "io_kbytes" : 1112279,
        "bw_bytes" : 37964524,
        "bw" : 37074,
        "iops" : 37074.730842,
        "runtime" : 30001,
        "total_ios" : 1112279,
        "short_ios" : 0,
        "drop_ios" : 0,
        "slat_ns" : {
          "min" : 17457,
          "max" : 6338697,
          "mean" : 25845.764651,
          "stddev" : 10892.888148,
          "N" : 1112279
        },
        "clat_ns" : {
          "min" : 2300,
          "max" : 6861473,
          "mean" : 189232.366226,
          "stddev" : 31855.634001,
          "N" : 1112279,
          "percentile" : {
            "1.000000" : 168960,
            "5.000000" : 171008,
            "10.000000" : 173056,
            "20.000000" : 175104,
            "30.000000" : 177152,
            "40.000000" : 179200,
            "50.000000" : 181248,
            "60.000000" : 183296,
            "70.000000" : 185344,
            "80.000000" : 189440,
            "90.000000" : 228352,
            "95.000000" : 238592,
            "99.000000" : 292864,
            "99.500000" : 329728,
            "99.900000" : 382976,
            "99.950000" : 403456,
            "99.990000" : 692224
          },
          "bins" : {
            "2288" : 1,
            "30080" : 1,
            "54016" : 1,
            "83456" : 1,
            "107008" : 1,
            "130560" : 1,
            "154624" : 1,
            "158720" : 2,
            "160768" : 12,
            "162816" : 191,
            "164864" : 1278,
            "166912" : 5764,
            "168960" : 17866,
            "171008" : 41779,
            "173056" : 75207,
            "175104" : 109093,
            "177152" : 130760,
            "179200" : 132673,
            "181248" : 117713,
            "183296" : 96018,
            "185344" : 73799,
            "187392" : 54318,
            "189440" : 37799,
            "191488" : 25186,
            "193536" : 16794,
            "195584" : 10920,
            "197632" : 7428,
            "199680" : 5117,
            "201728" : 3624,
            "203776" : 2684,
            "205824" : 1946,
            "207872" : 1618,
            "209920" : 1212,
            "211968" : 1098,
            "214016" : 906,
            "216064" : 1048,
            "218112" : 1368,
            "220160" : 2408,
            "222208" : 3933,
            "224256" : 6181,
            "226304" : 8259,
            "228352" : 10359,
            "230400" : 11704,
            "232448" : 11674,
            "234496" : 10816,
            "236544" : 9412,
            "238592" : 7711,
            "240640" : 6080,
            "242688" : 4711,
            "244736" : 3529,
            "246784" : 2746,
            "248832" : 2158,
            "250880" : 1727,
            "252928" : 1392,
            "254976" : 1151,
            "257024" : 989,
            "259072" : 817,
            "261120" : 645,
            "264192" : 1004,
            "268288" : 986,
            "272384" : 1872,
            "276480" : 3187,
            "280576" : 3356,
            "284672" : 3046,
            "288768" : 2408,
            "292864" : 1775,
            "296960" : 1207,
            "301056" : 963,
            "305152" : 708,
            "309248" : 470,
            "313344" : 302,
            "317440" : 213,
            "321536" : 337,
            "325632" : 844,
            "329728" : 942,
            "333824" : 826,
            "337920" : 661,
            "342016" : 525,
            "346112" : 466,
            "350208" : 347,
            "354304" : 286,
            "358400" : 169,
            "362496" : 123,
            "366592" : 105,
            "370688" : 58,
            "374784" : 111,
            "378880" : 182,
            "382976" : 139,
            "387072" : 130,
            "391168" : 137,
            "395264" : 86,
            "399360" : 89,
            "403456" : 82,
            "407552" : 73,
            "411648" : 48,
            "415744" : 37,
            "419840" : 27,
            "423936" : 30,
            "428032" : 23,
            "432128" : 19,
            "436224" : 18,
            "440320" : 6,
            "444416" : 11,
            "448512" : 12,
            "452608" : 13,
            "456704" : 10,
            "460800" : 13,
            "464896" : 4,
            "468992" : 5,
            "473088" : 2,
            "477184" : 3,
            "481280" : 2,
            "485376" : 2,
            "489472" : 1,
            "493568" : 1,
            "497664" : 1,
            "501760" : 3,
            "505856" : 6,
            "509952" : 3,
            "514048" : 2,
            "518144" : 1,
            "528384" : 2,
            "536576" : 2,
            "544768" : 1,
            "569344" : 2,
            "577536" : 3,
            "593920" : 7,
            "602112" : 1,
            "626688" : 1,
            "692224" : 3,
            "700416" : 2,
            "708608" : 2,
            "733184" : 1,
            "741376" : 2,
            "749568" : 2,
            "757760" : 1,
            "765952" : 3,
            "774144" : 2,
            "782336" : 1,
            "790528" : 1,
            "798720" : 1,
            "864256" : 1,
            "905216" : 1,
            "937984" : 1,
            "962560" : 1,
            "987136" : 1,
            "1003520" : 3,
            "1011712" : 1,
            "1019904" : 3,
            "1028096" : 1,
            "1036288" : 1,
            "1056768" : 1,
            "1073152" : 2,
            "1089536" : 1,
            "1105920" : 5,
            "1122304" : 1,
            "1138688" : 4,
            "1155072" : 7,
            "1171456" : 8,
            "1187840" : 4,
            "1204224" : 8,
            "1220608" : 4,
            "1236992" : 6,
            "1449984" : 1,
            "1466368" : 1,
            "1482752" : 4,
            "1499136" : 4,
            "1515520" : 2,
            "1531904" : 1,
            "1548288" : 5,
            "1564672" : 1,
            "6520832" : 1,
            "6586368" : 1,
            "6651904" : 3,
            "6782976" : 1,
            "6848512" : 1
          }
        },
        "lat_ns" : {
          "min" : 29257,
          "max" : 6933814,
          "mean" : 215226.958646,
          "stddev" : 34464.932061,
          "N" : 1112279
        },
        "bw_min" : 28830,
        "bw_max" : 39144,
        "bw_agg" : 100.000000,
        "bw_mean" : 37079.389831,
        "bw_dev" : 2382.063355,
        "bw_samples" : 59,
        "iops_min" : 28830,
        "iops_max" : 39144,
        "iops_mean" : 37079.389831,
        "iops_stddev" : 2382.063355,
        "iops_samples" : 59
      },
      "trim" : {
        "io_bytes" : 0,
        "io_kbytes" : 0,
        "bw_bytes" : 0,
        "bw" : 0,
        "iops" : 0.000000,
        "runtime" : 0,
        "total_ios" : 0,
        "short_ios" : 0,
        "drop_ios" : 0,
        "slat_ns" : {
          "min" : 0,
          "max" : 0,
          "mean" : 0.000000,
          "stddev" : 0.000000,
          "N" : 0
        },
        "clat_ns" : {
          "min" : 0,
          "max" : 0,
          "mean" : 0.000000,
          "stddev" : 0.000000,
          "N" : 0
        },
        "lat_ns" : {
          "min" : 0,
          "max" : 0,
          "mean" : 0.000000,
          "stddev" : 0.000000,
          "N" : 0
        },
        "bw_min" : 0,
        "bw_max" : 0,
        "bw_agg" : 0.000000,
        "bw_mean" : 0.000000,
        "bw_dev" : 0.000000,
        "bw_samples" : 0,
        "iops_min" : 0,
        "iops_max" : 0,
        "iops_mean" : 0.000000,
        "iops_stddev" : 0.000000,
        "iops_samples" : 0
      },
      "sync" : {
        "total_ios" : 0,
        "lat_ns" : {
          "min" : 0,
          "max" : 0,
          "mean" : 0.000000,
          "stddev" : 0.000000,
          "N" : 0
        }
      },
      "job_runtime" : 30000,
      "usr_cpu" : 4.623333,
      "sys_cpu" : 22.703333,
      "ctx" : 1113604,
      "majf" : 0,
      "minf" : 12,
      "iodepth_level" : {
        "1" : 0.100000,
        "2" : 0.100000,
        "4" : 0.100000,
        "8" : 99.999371,
        "16" : 0.000000,
        "32" : 0.000000,
        ">=64" : 0.000000
      },
      "iodepth_submit" : {
        "0" : 0.000000,
        "4" : 100.000000,
        "8" : 0.000000,
        "16" : 0.000000,
        "32" : 0.000000,
        "64" : 0.000000,
        ">=64" : 0.000000
      },
      "iodepth_complete" : {
        "0" : 0.000000,
        "4" : 99.999910,
        "8" : 0.100000,
        "16" : 0.000000,
        "32" : 0.000000,
        "64" : 0.000000,
        ">=64" : 0.000000
      },
      "latency_ns" : {
        "2" : 0.000000,
        "4" : 0.000000,
        "10" : 0.000000,
        "20" : 0.000000,
        "50" : 0.000000,
        "100" : 0.000000,
        "250" : 0.000000,
        "500" : 0.000000,
        "750" : 0.000000,
        "1000" : 0.000000
      },
      "latency_us" : {
        "2" : 0.000000,
        "4" : 0.010000,
        "10" : 0.000000,
        "20" : 0.000000,
        "50" : 0.010000,
        "100" : 0.010000,
        "250" : 96.832270,
        "500" : 3.154245,
        "750" : 0.010000,
        "1000" : 0.010000
      },
      "latency_ms" : {
        "2" : 0.010000,
        "4" : 0.000000,
        "10" : 0.010000,
        "20" : 0.000000,
        "50" : 0.000000,
        "100" : 0.000000,
        "250" : 0.000000,
        "500" : 0.000000,
        "750" : 0.000000,
        "1000" : 0.000000,
        "2000" : 0.000000,
        ">=2000" : 0.000000
      },
      "latency_depth" : 8,
      "latency_target" : 0,
      "latency_percentile" : 100.000000,
      "latency_window" : 0
    }
  ]
}
