{
  "fio version" : "fio-3.26-38-g3277",
  "timestamp" : 1622560104,
  "timestamp_ms" : 1622560104351,
  "time" : "Tue Jun  1 15:08:24 2021",
  "global options" : {
    "directory" : "/tmp/test-volume",
    "bs" : "32768",
    "fallocate" : "none",
    "runtime" : "30",
    "time_based" : "1",
    "ioengine" : "libaio",
    "iodepth" : "8",
    "direct" : "0",
    "buffered" : "1",
    "invalidate" : "1",
    "ramp_time" : "0",
    "thread" : "0",
    "numjobs" : "2",
    "group_reporting" : "1",
    "filesize" : "2G",
    "size" : "2G",
    "filename_format" : "$jobnum.dat"
  },
  "jobs" : [
    {
      "jobname" : "fio-job",
      "groupid" : 0,
      "error" : 0,
      "eta" : 0,
      "elapsed" : 31,
      "job options" : {
        "rw" : "read"
      },
      "read" : {
        "io_bytes" : 80453238784,
        "io_kbytes" : 78567616,
        "bw_bytes" : 2681685236,
        "bw" : 2618833,
        "iops" : 81838.538715,
        "runtime" : 30001,
        "total_ios" : 2455238,
        "short_ios" : 0,
        "drop_ios" : 0,
        "slat_ns" : {
          "min" : 3144,
          "max" : 6590341,
          "mean" : 18384.778586,
          "stddev" : 61800.039294,
          "N" : 2455238
        },
        "clat_ns" : {
          "min" : 1303,
          "max" : 344005453,
          "mean" : 171590.824306,
          "stddev" : 3360591.677878,
          "N" : 2455238,
          "percentile" : {
            "1.000000" : 34048,
            "5.000000" : 35072,
            "10.000000" : 41728,
            "20.000000" : 66048,
            "30.000000" : 72192,
            "40.000000" : 113152,
            "50.000000" : 146432,
            "60.000000" : 150528,
            "70.000000" : 156672,
            "80.000000" : 191488,
            "90.000000" : 228352,
            "95.000000" : 238592,
            "99.000000" : 309248,
            "99.500000" : 342016,
            "99.900000" : 2801664,
            "99.950000" : 3424256,
            "99.990000" : 320864256
          },
          "bins" : {
            "1304" : 1,
            "1480" : 1,
            "6368" : 1,
            "10944" : 1,
            "15808" : 1,
            "20864" : 1,
            "25216" : 1,
            "25984" : 1,
            "30848" : 1,
            "31104" : 7,
            "31360" : 7,
            "31616" : 8,
            "31872" : 42,
            "32128" : 128,
            "32384" : 328,
            "32640" : 754,
            "33024" : 5040,
            "33536" : 18083,
            "34048" : 39519,
            "34560" : 51368,
            "35072" : 44354,
            "35584" : 30166,
            "36096" : 18569,
            "36608" : 10412,
            "37120" : 5114,
            "37632" : 2526,
            "38144" : 1236,
            "38656" : 662,
            "39168" : 550,
            "39680" : 709,
            "40192" : 1652,
            "40704" : 3556,
            "41216" : 6196,
            "41728" : 7074,
            "42240" : 6037,
            "42752" : 4440,
            "43264" : 3148,
            "43776" : 2166,
            "44288" : 1458,
            "44800" : 1016,
            "45312" : 735,
            "45824" : 481,
            "46336" : 334,
            "46848" : 284,
            "47360" : 262,
            "47872" : 339,
            "48384" : 463,
            "48896" : 515,
            "49408" : 466,
            "49920" : 387,
            "50432" : 328,
            "50944" : 278,
            "51456" : 248,
            "51968" : 225,
            "52480" : 221,
            "52992" : 222,
            "53504" : 264,
            "54016" : 252,
            "54528" : 227,
            "55040" : 256,
            "55552" : 231,
            "56064" : 219,
            "56576" : 185,
            "57088" : 149,
            "57600" : 167,
            "58112" : 126,
            "58624" : 162,
            "59136" : 363,
            "59648" : 929,
            "60160" : 1853,
            "60672" : 2628,
            "61184" : 3923,
            "61696" : 6268,
            "62208" : 11577,
            "62720" : 19836,
            "63232" : 28031,
            "63744" : 32948,
            "64256" : 32595,
            "64768" : 29167,
            "65280" : 23886,
            "66048" : 31608,
            "67072" : 18731,
            "68096" : 17071,
            "69120" : 31838,
            "70144" : 63386,
            "71168" : 80321,
            "72192" : 63638,
            "73216" : 38690,
            "74240" : 23710,
            "75264" : 15640,
            "76288" : 12900,
            "77312" : 13667,
            "78336" : 13752,
            "79360" : 11136,
            "80384" : 7651,
            "81408" : 5710,
            "82432" : 4456,
            "83456" : 3672,
            "84480" : 3509,
            "85504" : 3380,
            "86528" : 3186,
            "87552" : 2836,
            "88576" : 2590,
            "89600" : 2274,
            "90624" : 2211,
            "91648" : 2063,
            "92672" : 1828,
            "93696" : 1790,
            "94720" : 1444,
            "95744" : 1393,
            "96768" : 1367,
            "97792" : 1304,
            "98816" : 1453,
            "99840" : 1515,
            "100864" : 1381,
            "101888" : 1378,
            "102912" : 1257,
            "103936" : 1152,
            "104960" : 1202,
            "105984" : 1348,
            "107008" : 1397,
            "108032" : 1631,
            "109056" : 1974,
            "110080" : 2242,
            "111104" : 2288,
            "112128" : 2438,
            "113152" : 2438,
            "114176" : 2534,
            "115200" : 2417,
            "116224" : 3057,
            "117248" : 3476,
            "118272" : 3323,
            "119296" : 3128,
            "120320" : 2708,
            "121344" : 2499,
            "122368" : 2283,
            "123392" : 2116,
            "124416" : 2055,
            "125440" : 1914,
            "126464" : 1890,
            "127488" : 1812,
            "128512" : 1903,
            "129536" : 2131,
            "130560" : 2437,
            "132096" : 7020,
            "134144" : 9216,
            "136192" : 10082,
            "138240" : 9221,
            "140288" : 8727,
            "142336" : 14826,
            "144384" : 60561,
            "146432" : 148462,
            "148480" : 161336,
            "150528" : 115931,
            "152576" : 80399,
            "154624" : 63982,
            "156672" : 49007,
            "158720" : 33809,
            "160768" : 21808,
            "162816" : 15503,
            "164864" : 12450,
            "166912" : 9491,
            "168960" : 7446,
            "171008" : 6018,
            "173056" : 4374,
            "175104" : 3330,
            "177152" : 2673,
            "179200" : 3238,
            "181248" : 6146,
            "183296" : 11854,
            "185344" : 16074,
            "187392" : 16737,
            "189440" : 16630,
            "191488" : 17506,
            "193536" : 17749,
            "195584" : 15728,
            "197632" : 13310,
            "199680" : 10748,
            "201728" : 9776,
            "203776" : 8397,
            "205824" : 7829,
            "207872" : 7709,
            "209920" : 7226,
            "211968" : 7034,
            "214016" : 8022,
            "216064" : 10735,
            "218112" : 15468,
            "220160" : 19890,
            "222208" : 22621,
            "224256" : 26608,
            "226304" : 30166,
            "228352" : 30292,
            "230400" : 28532,
            "232448" : 25368,
            "234496" : 21039,
            "236544" : 17363,
            "238592" : 12922,
            "240640" : 9876,
            "242688" : 7710,
            "244736" : 5812,
            "246784" : 4416,
            "248832" : 3328,
            "250880" : 2862,
            "252928" : 2192,
            "254976" : 1894,
            "257024" : 1579,
            "259072" : 1531,
            "261120" : 1881,
            "264192" : 4956,
            "268288" : 6677,
            "272384" : 6429,
            "276480" : 6058,
            "280576" : 5255,
            "284672" : 4217,
            "288768" : 3289,
            "292864" : 2238,
            "296960" : 1640,
            "301056" : 1533,
            "305152" : 2018,
            "309248" : 2745,
            "313344" : 3192,
            "317440" : 2366,
            "321536" : 1687,
            "325632" : 1192,
            "329728" : 728,
            "333824" : 616,
            "337920" : 463,
            "342016" : 336,
            "346112" : 293,
            "350208" : 287,
            "354304" : 276,
            "358400" : 303,
            "362496" : 293,
            "366592" : 311,
            "370688" : 262,
            "374784" : 332,
            "378880" : 223,
            "382976" : 277,
            "387072" : 249,
            "391168" : 236,
            "395264" : 274,
            "399360" : 155,
            "403456" : 118,
            "407552" : 98,
            "411648" : 97,
            "415744" : 65,
            "419840" : 73,
            "423936" : 78,
            "428032" : 50,
            "432128" : 46,
            "436224" : 49,
            "440320" : 48,
            "444416" : 45,
            "448512" : 46,
            "452608" : 45,
            "456704" : 41,
            "460800" : 30,
            "464896" : 31,
            "468992" : 32,
            "473088" : 38,
            "477184" : 31,
            "481280" : 14,
            "485376" : 44,
            "489472" : 21,
            "493568" : 9,
            "497664" : 17,
            "501760" : 30,
            "505856" : 8,
            "509952" : 21,
            "514048" : 12,
            "518144" : 9,
            "522240" : 16,
            "528384" : 40,
            "536576" : 31,
            "544768" : 49,
            "552960" : 35,
            "561152" : 32,
            "569344" : 43,
            "577536" : 28,
            "585728" : 26,
            "593920" : 26,
            "602112" : 18,
            "610304" : 32,
            "618496" : 16,
            "626688" : 5,
            "634880" : 30,
            "643072" : 13,
            "651264" : 8,
            "659456" : 26,
            "667648" : 26,
            "675840" : 29,
            "684032" : 16,
            "692224" : 36,
            "700416" : 23,
            "708608" : 32,
            "716800" : 13,
            "724992" : 7,
            "733184" : 15,
            "741376" : 8,
            "749568" : 19,
            "757760" : 21,
            "765952" : 22,
            "774144" : 16,
            "782336" : 15,
            "790528" : 16,
            "798720" : 25,
            "806912" : 18,
            "815104" : 15,
            "823296" : 3,
            "831488" : 36,
            "839680" : 11,
            "847872" : 21,
            "856064" : 17,
            "864256" : 1,
            "872448" : 20,
            "880640" : 30,
            "888832" : 14,
            "897024" : 16,
            "905216" : 38,
            "913408" : 14,
            "921600" : 21,
            "929792" : 24,
            "937984" : 26,
            "946176" : 37,
            "954368" : 17,
            "962560" : 14,
            "970752" : 15,
            "978944" : 23,
            "987136" : 19,
            "995328" : 34,
            "1003520" : 19,
            "1011712" : 20,
            "1019904" : 19,
            "1028096" : 10,
            "1036288" : 24,
            "1044480" : 23,
            "1056768" : 60,
            "1073152" : 55,
            "1089536" : 57,
            "1105920" : 42,
            "1122304" : 55,
            "1138688" : 29,
            "1155072" : 62,
            "1171456" : 57,
            "1187840" : 38,
            "1204224" : 37,
            "1220608" : 37,
            "1236992" : 41,
            "1253376" : 27,
            "1269760" : 28,
            "1286144" : 31,
            "1302528" : 34,
            "1318912" : 20,
            "1335296" : 46,
            "1351680" : 26,
            "1368064" : 25,
            "1384448" : 14,
            "1400832" : 45,
            "1417216" : 32,
            "1433600" : 33,
            "1449984" : 40,
            "1466368" : 26,
            "1482752" : 42,
            "1499136" : 17,
            "1515520" : 32,
            "1531904" : 15,
            "1548288" : 32,
            "1564672" : 27,
            "1581056" : 42,
            "1597440" : 38,
            "1613824" : 25,
            "1630208" : 34,
            "1646592" : 30,
            "1662976" : 27,
            "1679360" : 15,
            "1695744" : 18,
            "1712128" : 26,
            "1728512" : 47,
            "1744896" : 13,
            "1761280" : 25,
            "1777664" : 27,
            "1794048" : 23,
            "1810432" : 32,
            "1826816" : 22,
            "1843200" : 17,
            "1859584" : 32,
            "1875968" : 66,
            "1892352" : 55,
            "1908736" : 26,
            "1925120" : 41,
            "1941504" : 35,
            "1957888" : 5,
            "1974272" : 17,
            "1990656" : 27,
            "2007040" : 21,
            "2023424" : 22,
            "2039808" : 29,
            "2056192" : 38,
            "2072576" : 21,
            "2088960" : 46,
            "2113536" : 86,
            "2146304" : 75,
            "2179072" : 23,
            "2211840" : 35,
            "2244608" : 72,
            "2277376" : 61,
            "2310144" : 46,
            "2342912" : 58,
            "2375680" : 102,
            "2408448" : 53,
            "2441216" : 42,
            "2473984" : 40,
            "2506752" : 69,
            "2539520" : 47,
            "2572288" : 60,
            "2605056" : 70,
            "2637824" : 42,
            "2670592" : 79,
            "2703360" : 36,
            "2736128" : 79,
            "2768896" : 55,
            "2801664" : 59,
            "2834432" : 65,
            "2867200" : 53,
            "2899968" : 96,
            "2932736" : 69,
            "2965504" : 69,
            "2998272" : 58,
            "3031040" : 93,
            "3063808" : 29,
            "3096576" : 59,
            "3129344" : 61,
            "3162112" : 109,
            "3194880" : 53,
            "3227648" : 90,
            "3260416" : 70,
            "3293184" : 64,
            "3325952" : 49,
            "3358720" : 34,
            "3391488" : 60,
            "3424256" : 56,
            "3457024" : 62,
            "3489792" : 37,
            "3522560" : 67,
            "3555328" : 16,
            "3588096" : 37,
            "3620864" : 32,
            "3653632" : 54,
            "3686400" : 54,
            "3719168" : 75,
            "3751936" : 75,
            "3784704" : 43,
            "3817472" : 18,
            "3850240" : 21,
            "3883008" : 30,
            "3915776" : 55,
            "3948544" : 43,
            "3981312" : 15,
            "4014080" : 1,
            "4046848" : 7,
            "4079616" : 27,
            "4112384" : 71,
            "4145152" : 35,
            "4177920" : 29,
            "4227072" : 11,
            "6586368" : 7,
            "6651904" : 7,
            "316669952" : 2,
            "320864256" : 12,
            "325058560" : 37,
            "329252864" : 82,
            "333447168" : 64,
            "337641472" : 34,
            "341835776" : 16,
            "346030080" : 5
          }
        },
        "lat_ns" : {
          "min" : 5630,
          "max" : 344009795,
          "mean" : 190140.772672,
          "stddev" : 3360686.588859,
          "N" : 2455238
        },
        "bw_min" : 1059904,
        "bw_max" : 3332672,
        "bw_agg" : 99.608977,
        "bw_mean" : 2608593.355932,
        "bw_dev" : 400918.361008,
        "bw_samples" : 118,
        "iops_min" : 33122,
        "iops_max" : 104146,
        "iops_mean" : 81518.542373,
        "iops_stddev" : 12528.698781,
        "iops_samples" : 118
      },
      "write" : {
        "io_bytes" : 0,
        "io_kbytes" : 0,
        "bw_bytes" : 0,
        "bw" : 0,
        "iops" : 0.000000,
        "runtime" : 0,
        "total_ios" : 0,
        "short_ios" : 0,
        "drop_ios" : 0,
        "slat_ns" : {
          "min" : 0,
          "max" : 0,
          "mean" : 0.000000,
          "stddev" : 0.000000,
          "N" : 0
        },
        "clat_ns" : {
          "min" : 0,
          "max" : 0,
          "mean" : 0.000000,
          "stddev" : 0.000000,
          "N" : 0
        },
        "lat_ns" : {
          "min" : 0,
          "max" : 0,
          "mean" : 0.000000,
          "stddev" : 0.000000,
          "N" : 0
        },
        "bw_min" : 0,
        "bw_max" : 0,
        "bw_agg" : 0.000000,
        "bw_mean" : 0.000000,
        "bw_dev" : 0.000000,
        "bw_samples" : 0,
        "iops_min" : 0,
        "iops_max" : 0,
        "iops_mean" : 0.000000,
        "iops_stddev" : 0.000000,
        "iops_samples" : 0
      },
      "trim" : {
        "io_bytes" : 0,
        "io_kbytes" : 0,
        "bw_bytes" : 0,
        "bw" : 0,
        "iops" : 0.000000,
        "runtime" : 0,
        "total_ios" : 0,
        "short_ios" : 0,
        "drop_ios" : 0,
        "slat_ns" : {
          "min" : 0,
          "max" : 0,
          "mean" : 0.000000,
          "stddev" : 0.000000,
          "N" : 0
        },
        "clat_ns" : {
          "min" : 0,
          "max" : 0,
          "mean" : 0.000000,
          "stddev" : 0.000000,
          "N" : 0
        },
        "lat_ns" : {
          "min" : 0,
          "max" : 0,
          "mean" : 0.000000,
          "stddev" : 0.000000,
          "N" : 0
        },
        "bw_min" : 0,
        "bw_max" : 0,
        "bw_agg" : 0.000000,
        "bw_mean" : 0.000000,
        "bw_dev" : 0.000000,
        "bw_samples" : 0,
        "iops_min" : 0,
        "iops_max" : 0,
        "iops_mean" : 0.000000,
        "iops_stddev" : 0.000000,
        "iops_samples" : 0
      },
      "sync" : {
        "total_ios" : 0,
        "lat_ns" : {
          "min" : 0,
          "max" : 0,
          "mean" : 0.000000,
          "stddev" : 0.000000,
          "N" : 0
        }
      },
      "job_runtime" : 60000,
      "usr_cpu" : 3.001667,
      "sys_cpu" : 39.668333,
      "ctx" : 327128,
      "majf" : 0,
      "minf" : 155,
      "iodepth_level" : {
        "1" : 0.100000,
        "2" : 0.100000,
        "4" : 0.100000,
        "8" : 99.999430,
        "16" : 0.000000,
        "32" : 0.000000,
        ">=64" : 0.000000
      },
      "iodepth_submit" : {
        "0" : 0.000000,
        "4" : 100.000000,
        "8" : 0.000000,
        "16" : 0.000000,
        "32" : 0.000000,
        "64" : 0.000000,
        ">=64" : 0.000000
      },
      "iodepth_complete" : {
        "0" : 0.000000,
        "4" : 99.999919,
        "8" : 0.100000,
        "16" : 0.000000,
        "32" : 0.000000,
        "64" : 0.000000,
        ">=64" : 0.000000
      },
      "latency_ns" : {
        "2" : 0.000000,
        "4" : 0.000000,
        "10" : 0.000000,
        "20" : 0.000000,
        "50" : 0.000000,
        "100" : 0.000000,
        "250" : 0.000000,
        "500" : 0.000000,
        "750" : 0.000000,
        "1000" : 0.000000
      },
      "latency_us" : {
        "2" : 0.010000,
        "4" : 0.000000,
        "10" : 0.010000,
        "20" : 0.010000,
        "50" : 11.015877,
        "100" : 28.064611,
        "250" : 57.594865,
        "500" : 3.026998,
        "750" : 0.031321,
        "1000" : 0.024763
      },
      "latency_ms" : {
        "2" : 0.083251,
        "4" : 0.139905,
        "10" : 0.010000,
        "20" : 0.000000,
        "50" : 0.000000,
        "100" : 0.000000,
        "250" : 0.000000,
        "500" : 0.010264,
        "750" : 0.000000,
        "1000" : 0.000000,
        "2000" : 0.000000,
        ">=2000" : 0.000000
      },
      "latency_depth" : 8,
      "latency_target" : 0,
      "latency_percentile" : 100.000000,
      "latency_window" : 0
    }
  ]
}
